{
  "total": 3217251,
  "by_category": {
    "Digital": 8567,
    "Exhibition": 1745407,
    "Festival": 10863,
    "Film": 25075,
    "In-person": 1401565,
    "UNKNOWN": 25774
  },
  "by_project": {
    "'Creative Thinkers' in Your Classroom": {
      "category": "UNKNOWN",
      "count": 81
    },
    "A Good Yarn: Luke Jerram": {
      "category": "Exhibition, In-person",
      "count": 13979
    },
    "A Portrait of Us - Outdoor Exhibition": {
      "category": "Exhibition",
      "count": 718630
    },
    "A Somali Village in Lister Park: Friends of Bradford Art Galleries and Museums": {
      "category": "In-person",
      "count": 90
    },
    "A World Without Death": {
      "category": "In-person",
      "count": 792
    },
    "Akram Khan and Dance United - Memories of the Future": {
      "category": "In-person",
      "count": 1060
    },
    "Alfred Bradley Bursary Award (ABBA)": {
      "category": "UNKNOWN",
      "count": 55
    },
    "An Evening with Resi/Dance @ The Beacon (Dance United)": {
      "category": "In-person",
      "count": 86
    },
    "An Evening with The Beehive Poets: Poetry Playground": {
      "category": "UNKNOWN",
      "count": 36
    },
    "An Evening with: Jacqui Dankworth": {
      "category": "In-person",
      "count": 155
    },
    "Ang\u00e9lique Kidjo: African Symphony": {
      "category": "UNKNOWN",
      "count": 1341
    },
    "Antony Szmierek": {
      "category": "UNKNOWN",
      "count": 387
    },
    "Ark": {
      "category": "In-person",
      "count": 100
    },
    "Ark Bradford: Storm Gathering": {
      "category": "UNKNOWN",
      "count": 122
    },
    "Aswad Arts Presents StreetSounds \"LIVE\" Bhangra Niche Set \"LIVE\"": {
      "category": "In-person",
      "count": 86
    },
    "At The 1 in 12": {
      "category": "In-person",
      "count": 159
    },
    "BBC Contains Strong Language": {
      "category": "Festival",
      "count": 4001
    },
    "BBC Extraordinary Portraits": {
      "category": "Exhibition",
      "count": 11004
    },
    "BBC Introducing @ The Beacon": {
      "category": "In-person",
      "count": 126
    },
    "BBC Introducing Panel": {
      "category": "UNKNOWN",
      "count": 44
    },
    "BBC Introducing Showcase": {
      "category": "UNKNOWN",
      "count": 214
    },
    "BBC Introducing at The Underground": {
      "category": "In-person",
      "count": 139
    },
    "BBC Radio 4 Beyond Belief": {
      "category": "UNKNOWN",
      "count": 129
    },
    "BBC Radio 4 Front Row": {
      "category": "UNKNOWN",
      "count": 388
    },
    "BBC Radio 4 Loose Ends": {
      "category": "UNKNOWN",
      "count": 836
    },
    "BBC Radio 4 Start the Week": {
      "category": "UNKNOWN",
      "count": 171
    },
    "BBC Radio 4 The Adverb": {
      "category": "UNKNOWN",
      "count": 299
    },
    "BBC Radio Club": {
      "category": "UNKNOWN",
      "count": 86
    },
    "BBC Writers: Who We Are & What We Do": {
      "category": "UNKNOWN",
      "count": 59
    },
    "BBC: Not Even Water Live (Podcast Recording)": {
      "category": "In-person",
      "count": 40
    },
    "BD Festival 2025": {
      "category": "In-person",
      "count": 40000
    },
    "BD is Lit 2023": {
      "category": "In-person",
      "count": 32000
    },
    "BD: Is LIT 2025": {
      "category": "Exhibition",
      "count": 30000
    },
    "BOLD! Bradford Artist Scratch Night": {
      "category": "In-person",
      "count": 33
    },
    "Babysphere & Colorsphere": {
      "category": "In-person",
      "count": 424
    },
    "Back In The Pink - Castles In The Sky": {
      "category": "Exhibition, Film, In-person",
      "count": 780
    },
    "Back in The Pink: Big Nights OUT": {
      "category": "UNKNOWN",
      "count": 51
    },
    "Back in The Pink: Cinema Special": {
      "category": "UNKNOWN",
      "count": 34
    },
    "Back in The Pink: LGBTQ+ History Walking Tour": {
      "category": "UNKNOWN",
      "count": 30
    },
    "Back in the Pink: Pink After Dark": {
      "category": "UNKNOWN",
      "count": 145
    },
    "Bantam of the Opera": {
      "category": "In-person",
      "count": 32033
    },
    "Bantam's Drift": {
      "category": "UNKNOWN",
      "count": 135
    },
    "Basel Zaraa - Moomins": {
      "category": "In-person",
      "count": 983
    },
    "Bassline Symphony": {
      "category": "In-person",
      "count": 60
    },
    "Baton of Hope": {
      "category": "In-person",
      "count": 682
    },
    "Beacon": {
      "category": "In-person",
      "count": 681
    },
    "Big Bradford WESTival Celebration of Culture and Community": {
      "category": "In-person",
      "count": 149
    },
    "Big Brass Blowout": {
      "category": "Festival",
      "count": 2444
    },
    "Big Quiffy Bingo": {
      "category": "In-person",
      "count": 62
    },
    "Blankets & Wine Festival Bradford": {
      "category": "In-person",
      "count": 547
    },
    "Bloom": {
      "category": "In-person",
      "count": 6967
    },
    "Book Making": {
      "category": "UNKNOWN",
      "count": 3
    },
    "Book of Bradford Launch": {
      "category": "UNKNOWN",
      "count": 135
    },
    "Bradford A City Of Film: A Screen Near You - The Incredible Moving Cinema": {
      "category": "Film",
      "count": 1004
    },
    "Bradford A City of Film: Big Screen @Cannon Mills": {
      "category": "Film",
      "count": 1076
    },
    "Bradford A City of Film: Big Screen @Ilkley Lido": {
      "category": "Film",
      "count": 650
    },
    "Bradford A City of Film: Big Screen@ Thornton Viaduct": {
      "category": "Film",
      "count": 237
    },
    "Bradford Belles": {
      "category": "In-person",
      "count": 146
    },
    "Bradford DNA by Razwan Ul-Haq": {
      "category": "In-person",
      "count": 43967
    },
    "Bradford Digital Creatives (BDC)": {
      "category": "In-person",
      "count": 35275
    },
    "Bradford Glow": {
      "category": "In-person",
      "count": 274
    },
    "Bradford Literature Festival @ Loading Bay": {
      "category": "In-person",
      "count": 60
    },
    "Bradford Made": {
      "category": "In-person",
      "count": 154
    },
    "Bradford On Foot": {
      "category": "Digital",
      "count": 3776
    },
    "Bradford Open Mic Night": {
      "category": "UNKNOWN",
      "count": 61
    },
    "Bradford Poetry Slam 2025": {
      "category": "In-person",
      "count": 110
    },
    "Bradford Resource Centre archiving": {
      "category": "Exhibition, In-person",
      "count": 366
    },
    "Bradford Roots: Echoes of the Past, Inspiring Tomorrow\u2019s Voices by Sinead Campbell - Artist Led Project": {
      "category": "In-person",
      "count": 131
    },
    "Bradford Selection": {
      "category": "In-person",
      "count": 1383
    },
    "Bradford on Foot": {
      "category": "In-person",
      "count": 12912
    },
    "Brass on a Sunday Afternoon ": {
      "category": "UNKNOWN",
      "count": 227
    },
    "Bring it Back by Natalie Davies": {
      "category": "In-person",
      "count": 440
    },
    "Built By Sound": {
      "category": "In-person",
      "count": 332
    },
    "CANCELLED Stick in the Wheel": {
      "category": "In-person",
      "count": 1
    },
    "CBeebies Bedtime Story Day": {
      "category": "In-person",
      "count": 930
    },
    "CHANNELS": {
      "category": "Digital",
      "count": 1130
    },
    "CSL Poetry Gala: Part I": {
      "category": "UNKNOWN",
      "count": 170
    },
    "CSL Poetry Gala: Part II": {
      "category": "UNKNOWN",
      "count": 183
    },
    "CSL Poetry Shorts: Love in the 21st Century": {
      "category": "UNKNOWN",
      "count": 67
    },
    "CSL Poetry Shorts: Migration & Belonging": {
      "category": "UNKNOWN",
      "count": 65
    },
    "CSL Poetry Shorts: Mills & Hills": {
      "category": "UNKNOWN",
      "count": 58
    },
    "CSL Poetry Shorts: Mind & Body": {
      "category": "UNKNOWN",
      "count": 68
    },
    "CSL Poetry Shorts: Music & Lyrics": {
      "category": "UNKNOWN",
      "count": 68
    },
    "CSL Poetry Shorts: Poetic Justice": {
      "category": "UNKNOWN",
      "count": 69
    },
    "CSL Poetry Shorts: The Power of the Women of Bradford": {
      "category": "UNKNOWN",
      "count": 62
    },
    "CSL Poetry Shorts: Words in the Wild": {
      "category": "UNKNOWN",
      "count": 65
    },
    "Camille O'Sullivan": {
      "category": "In-person",
      "count": 175
    },
    "Celebrations of Bradford 2025 and LNER Partnership": {
      "category": "In-person",
      "count": 120
    },
    "Charlotte Bront\u00eb: Senseless Trash": {
      "category": "UNKNOWN",
      "count": 29
    },
    "Chasing Sunlight": {
      "category": "UNKNOWN",
      "count": 267
    },
    "Chasing the Wind": {
      "category": "In-person",
      "count": 110
    },
    "Claytime": {
      "category": "In-person",
      "count": 227
    },
    "Cliffe Castle Park 75th Birthday Bash": {
      "category": "In-person",
      "count": 3253
    },
    "Cocoa Butter Club": {
      "category": "In-person",
      "count": 73
    },
    "Come Rest in Chaos": {
      "category": "In-person",
      "count": 42
    },
    "Comma Press 'Book of the City'": {
      "category": "In-person",
      "count": 64
    },
    "Common/Wealth: Public Interest": {
      "category": "In-person",
      "count": 1051
    },
    "Compagnie Off: Giraffes": {
      "category": "In-person",
      "count": 5232
    },
    "Cool Runnings": {
      "category": "UNKNOWN",
      "count": 164
    },
    "Creative Careers Festival": {
      "category": "In-person",
      "count": 49
    },
    "Creative Cities Convention": {
      "category": "In-person",
      "count": 436
    },
    "Creative Summer Social (Cultural Voice Forum)": {
      "category": "In-person",
      "count": 58
    },
    "Crepe Paper Flower-Making": {
      "category": "UNKNOWN",
      "count": 1
    },
    "Cultural Learning One-Off Activity": {
      "category": "In-person",
      "count": 155
    },
    "Curious Investigators": {
      "category": "In-person",
      "count": 245
    },
    "DANCE SUITE": {
      "category": "UNKNOWN",
      "count": 257
    },
    "DJ Marco - Balkan Beats & Brass": {
      "category": "UNKNOWN",
      "count": 197
    },
    "Dancing with Colours": {
      "category": "In-person",
      "count": 47
    },
    "David Hockney: Pieced Together": {
      "category": "Exhibition",
      "count": 24007
    },
    "Dhamaal \u2013 Core": {
      "category": "UNKNOWN",
      "count": 258
    },
    "Dracula": {
      "category": "In-person",
      "count": 705
    },
    "Drag-Ford: Pre-Show Workshop": {
      "category": "UNKNOWN",
      "count": 18
    },
    "Drag-ford: Drag Cabaret Built in Bradford": {
      "category": "In-person",
      "count": 56
    },
    "Dragons - Eun-Me Ahn Company": {
      "category": "In-person",
      "count": 1274
    },
    "Earth & Sky (part of Wild Uplands)": {
      "category": "Exhibition, In-person",
      "count": 3082
    },
    "Echoes of the North": {
      "category": "UNKNOWN",
      "count": 271
    },
    "Eggs Collective Dark Nights": {
      "category": "In-person",
      "count": 130
    },
    "Elevate - Heritage Skills Project": {
      "category": "Exhibition, In-person",
      "count": 474
    },
    "Eliza Carthy": {
      "category": "In-person",
      "count": 175
    },
    "Elmet": {
      "category": "In-person",
      "count": 1295
    },
    "Embedding the Arts in Your School": {
      "category": "UNKNOWN",
      "count": 19
    },
    "Endless Hum": {
      "category": "In-person",
      "count": 158
    },
    "Evening Conversations": {
      "category": "UNKNOWN",
      "count": 162
    },
    "Everything for Everyone": {
      "category": "UNKNOWN",
      "count": 195
    },
    "FRESH 2025 - Workshops and Matinee Stage Performance": {
      "category": "In-person",
      "count": 518
    },
    "Festival of Archaeology: Archaeology Talks!": {
      "category": "Festival",
      "count": 564
    },
    "Fighting To Be Heard": {
      "category": "Exhibition",
      "count": 15917
    },
    "Film Culture in Bradford and Keighley: Friends of Bradford Art Galleries and Museums": {
      "category": "In-person",
      "count": 29
    },
    "Film: Amar Akbar Anthony": {
      "category": "UNKNOWN",
      "count": 63
    },
    "Film: Bajrangi Bhaijaan": {
      "category": "UNKNOWN",
      "count": 22
    },
    "Film: Barbie": {
      "category": "UNKNOWN",
      "count": 127
    },
    "Film: Big Hero 6": {
      "category": "UNKNOWN",
      "count": 140
    },
    "Film: Bride and Prejudice": {
      "category": "UNKNOWN",
      "count": 48
    },
    "Film: Conclave": {
      "category": "UNKNOWN",
      "count": 129
    },
    "Film: Dil Dhadakne Do": {
      "category": "UNKNOWN",
      "count": 11
    },
    "Film: Everybody's Talking About Jamie": {
      "category": "UNKNOWN",
      "count": 410
    },
    "Film: Everything Everywhere All at Once": {
      "category": "UNKNOWN",
      "count": 96
    },
    "Film: Fantastic Mr. Fox": {
      "category": "UNKNOWN",
      "count": 109
    },
    "Film: Flow": {
      "category": "UNKNOWN",
      "count": 272
    },
    "Film: Jab We Met": {
      "category": "UNKNOWN",
      "count": 126
    },
    "Film: Pulp Fiction": {
      "category": "UNKNOWN",
      "count": 50
    },
    "Film: Sexy Beast": {
      "category": "UNKNOWN",
      "count": 374
    },
    "Film: Speed": {
      "category": "UNKNOWN",
      "count": 95
    },
    "Film: The Apartment": {
      "category": "UNKNOWN",
      "count": 9
    },
    "Film: The Apartment ": {
      "category": "UNKNOWN",
      "count": 11
    },
    "Film: The Grand Budapest Hotel": {
      "category": "UNKNOWN",
      "count": 384
    },
    "Film: The Greatest Showman": {
      "category": "UNKNOWN",
      "count": 205
    },
    "Film: The Lorax": {
      "category": "UNKNOWN",
      "count": 177
    },
    "Film: The Matrix": {
      "category": "UNKNOWN",
      "count": 101
    },
    "Film: The Terminator": {
      "category": "UNKNOWN",
      "count": 35
    },
    "Film: The Wild Robot": {
      "category": "UNKNOWN",
      "count": 75
    },
    "Film: Zindagi Na Milegi Dobara": {
      "category": "UNKNOWN",
      "count": 39
    },
    "Forward Prize Launch": {
      "category": "UNKNOWN",
      "count": 83
    },
    "Four Nations Outdoor Arts Bursary 2025": {
      "category": "In-person",
      "count": 210
    },
    "Frontline 1984-1985 by Victor Wedderburn": {
      "category": "Exhibition",
      "count": 76942
    },
    "Gaana Shaana - Open Mic": {
      "category": "In-person",
      "count": 41
    },
    "Get Seen, Get Hired: Build a Creative Career Online": {
      "category": "UNKNOWN",
      "count": 30
    },
    "Ginger Johnson's Fun House": {
      "category": "In-person",
      "count": 174
    },
    "Greed": {
      "category": "In-person",
      "count": 29
    },
    "Grue Audio Description - Penfriend Kit": {
      "category": "UNKNOWN",
      "count": 39
    },
    "Hall Royd Brass Band": {
      "category": "UNKNOWN",
      "count": 227
    },
    "Happy Hype": {
      "category": "In-person",
      "count": 39
    },
    "Hardy and Free": {
      "category": "Exhibition, In-person",
      "count": 200000
    },
    "Here We Stand": {
      "category": "Exhibition",
      "count": 500
    },
    "Hindu Sangh Culture Event": {
      "category": "In-person",
      "count": 188
    },
    "Holding Space Conference: Arts, Refugees and Mental Health National Gathering": {
      "category": "In-person",
      "count": 90
    },
    "Holocene": {
      "category": "UNKNOWN",
      "count": 356
    },
    "Honk! Bradford by Peace Artistes": {
      "category": "In-person",
      "count": 4657
    },
    "Hot Caribbean Beatz in the Park": {
      "category": "In-person",
      "count": 188
    },
    "How to Get Published": {
      "category": "UNKNOWN",
      "count": 196
    },
    "I AM ME": {
      "category": "In-person",
      "count": 23224
    },
    "Ice Age Art Now": {
      "category": "Exhibition",
      "count": 25755
    },
    "Imaginary Friends": {
      "category": "In-person",
      "count": 40
    },
    "Immersive Arts UK Conference - The Big Thing": {
      "category": "Festival",
      "count": 149
    },
    "In Conversation with Ann Hamilton and Guests": {
      "category": "UNKNOWN",
      "count": 97
    },
    "International Roma Day Celebration": {
      "category": "In-person",
      "count": 67
    },
    "Into the Night": {
      "category": "UNKNOWN",
      "count": 643
    },
    "Intro to Comedy Workshop Series with Alex Dunlop": {
      "category": "In-person",
      "count": 102
    },
    "It's Your Round": {
      "category": "In-person",
      "count": 89
    },
    "Jameel Prize: Moving Images": {
      "category": "Exhibition",
      "count": 17104
    },
    "Journeys with Mai": {
      "category": "Exhibition",
      "count": 17104
    },
    "Jungle Book ReImagined - Akram Khan Company": {
      "category": "In-person",
      "count": 1794
    },
    "KOKOROKO": {
      "category": "UNKNOWN",
      "count": 1170
    },
    "Kailey": {
      "category": "In-person",
      "count": 234
    },
    "Kennet Canal Boat Play by Northern Duck Productions": {
      "category": "In-person",
      "count": 290
    },
    "Khooghi": {
      "category": "In-person",
      "count": 157
    },
    "La Haine - Asian Dub Foundation": {
      "category": "UNKNOWN",
      "count": 1144
    },
    "Lady Maisery / O'Hooley & Tidow": {
      "category": "In-person",
      "count": 183
    },
    "Language No Broblem: Shubbak Festival": {
      "category": "In-person",
      "count": 106
    },
    "Language is a Queer Thing Showcase": {
      "category": "UNKNOWN",
      "count": 112
    },
    "Language is a Queer Thing Workshop": {
      "category": "UNKNOWN",
      "count": 15
    },
    "Language: no broblem": {
      "category": "UNKNOWN",
      "count": 133
    },
    "Lanre Bakare - 'We Were There' Book Launch": {
      "category": "UNKNOWN",
      "count": 198
    },
    "Last Rites": {
      "category": "In-person",
      "count": 80
    },
    "Lay Down Your Burdens": {
      "category": "In-person",
      "count": 123
    },
    "Leeds Piano Competition 2024": {
      "category": "In-person",
      "count": 1690
    },
    "Leeds School of Architecture x Bradford 2025 - The City As a Festival": {
      "category": "Exhibition",
      "count": 88
    },
    "Leeds Young Film Festival: INDIs Filmmaker Award": {
      "category": "UNKNOWN",
      "count": 57
    },
    "Les Enfants Terribles - A Gameshow for Awful Children": {
      "category": "In-person",
      "count": 150
    },
    "Life Class (509 Arts)": {
      "category": "In-person",
      "count": 1138
    },
    "Life Class: Cuppa T": {
      "category": "UNKNOWN",
      "count": 77
    },
    "Lighthouse": {
      "category": "UNKNOWN",
      "count": 656
    },
    "Listen In: Jeremy Dyson & Mark Gatiss": {
      "category": "UNKNOWN",
      "count": 965
    },
    "Listen In: Nick Ahad": {
      "category": "UNKNOWN",
      "count": 87
    },
    "Little Wimmin": {
      "category": "In-person",
      "count": 129
    },
    "Loaded Laughs (#1)": {
      "category": "In-person",
      "count": 164
    },
    "Loaded Laughs (#2)": {
      "category": "In-person",
      "count": 120
    },
    "Loaded Laughs (#3)": {
      "category": "In-person",
      "count": 125
    },
    "Loaded Laughs (#4)": {
      "category": "In-person",
      "count": 161
    },
    "Loading Bay Programme": {
      "category": "In-person",
      "count": 70
    },
    "Loud and Proud Dohl Drumming": {
      "category": "In-person",
      "count": 140
    },
    "Love. Unite. Freedom": {
      "category": "UNKNOWN",
      "count": 185
    },
    "MARCH": {
      "category": "UNKNOWN",
      "count": 233
    },
    "Mango Season by Double Pivot": {
      "category": "In-person",
      "count": 5000
    },
    "Meet Our Mothers": {
      "category": "In-person",
      "count": 1679
    },
    "Mercury Songs": {
      "category": "UNKNOWN",
      "count": 290
    },
    "Moth x Human": {
      "category": "UNKNOWN",
      "count": 235
    },
    "Multicultural Pentecost Party": {
      "category": "In-person",
      "count": 1473
    },
    "Museums for Play and Growth": {
      "category": "In-person",
      "count": 122
    },
    "My Thousand Year Old Land": {
      "category": "In-person",
      "count": 57
    },
    "Nationhood: Memory and Hope": {
      "category": "Exhibition",
      "count": 17756
    },
    "New Focus: Bradford Young Curators": {
      "category": "Exhibition",
      "count": 10717
    },
    "New Music Biennial": {
      "category": "Festival",
      "count": 3166
    },
    "Nisbet Road Tailor's Shop": {
      "category": "Exhibition",
      "count": 908
    },
    "Nocturnal Sun": {
      "category": "UNKNOWN",
      "count": 182
    },
    "North Street Band": {
      "category": "UNKNOWN",
      "count": 82
    },
    "Northern Soul (Clio Barnard)": {
      "category": "Film",
      "count": 869
    },
    "N\u2019dehou": {
      "category": "UNKNOWN",
      "count": 226
    },
    "OFMS: John Grant @ St Georges Hall": {
      "category": "In-person",
      "count": 636
    },
    "OFMS: Nadine Shah @ St. Georges Hall": {
      "category": "In-person",
      "count": 650
    },
    "Open-Air Cinema: Milner Field": {
      "category": "UNKNOWN",
      "count": 237
    },
    "Opera North Earth and Sky": {
      "category": "Digital",
      "count": 3661
    },
    "Oranje Brass \u2013 Amazing Music From The Netherlands": {
      "category": "UNKNOWN",
      "count": 187
    },
    "Otherhood by Old Bird (Deborah Pakkar-Hull and Emma Adams)": {
      "category": "In-person",
      "count": 62
    },
    "Our Patch": {
      "category": "In-person",
      "count": 22827
    },
    "Our Story": {
      "category": "In-person",
      "count": 78
    },
    "Our Turn: Visual Arts Festival": {
      "category": "Exhibition",
      "count": 1329
    },
    "PLAY: Grue": {
      "category": "In-person",
      "count": 1789
    },
    "PLAY: Intergenerational Play": {
      "category": "In-person",
      "count": 42
    },
    "PLAY: Island of Foam (WOW)": {
      "category": "In-person",
      "count": 3000
    },
    "PLAY: Playable Commission": {
      "category": "In-person",
      "count": 10537
    },
    "PLAY: Red Ball Project (WOW)": {
      "category": "In-person",
      "count": 28623
    },
    "PLAY: Replay": {
      "category": "In-person",
      "count": 5651
    },
    "PLAY: The Great Adventure Build - Community Slots": {
      "category": "UNKNOWN",
      "count": 128
    },
    "PLAY: The Great Adventure Build - Home Education": {
      "category": "UNKNOWN",
      "count": 54
    },
    "PLAY: The Great Adventure Build - Schools": {
      "category": "UNKNOWN",
      "count": 128
    },
    "PLAY: The Great Adventure Build with Woodland Tribe": {
      "category": "In-person",
      "count": 2146
    },
    "Painting the Sky": {
      "category": "In-person",
      "count": 11000
    },
    "Palettes": {
      "category": "In-person",
      "count": 778
    },
    "Palingenesis": {
      "category": "In-person",
      "count": 78
    },
    "Penguin": {
      "category": "In-person",
      "count": 161
    },
    "Penguin Books 16+ Panel": {
      "category": "In-person",
      "count": 45
    },
    "Penumbra": {
      "category": "UNKNOWN",
      "count": 182
    },
    "People First Keighley and Craven Summer Party": {
      "category": "In-person",
      "count": 61
    },
    "Peregrinations: Urban Nature Poetry Walk": {
      "category": "UNKNOWN",
      "count": 31
    },
    "Pictureville Screenings": {
      "category": "Film",
      "count": 19985
    },
    "Pictureville Screenings - Epic Yorkshire Season": {
      "category": "Film",
      "count": 950
    },
    "Pictureville Screenings - Northern Youth Film Season": {
      "category": "Film",
      "count": 231
    },
    "Pictureville Screenings - Time and Place (Invisible Women)": {
      "category": "Film",
      "count": 44
    },
    "Pins For Peace by Mek Summat": {
      "category": "In-person",
      "count": 14000
    },
    "Plug It Up -Yorkshire Sound Women Network": {
      "category": "In-person",
      "count": 209
    },
    "Poetry Takeaway": {
      "category": "In-person",
      "count": 50
    },
    "Pop": {
      "category": "In-person",
      "count": 137
    },
    "Pop Up Family Pride": {
      "category": "In-person",
      "count": 732
    },
    "Public Interest Club Night": {
      "category": "UNKNOWN",
      "count": 53
    },
    "Public Interest: Access Opening Event": {
      "category": "UNKNOWN",
      "count": 3
    },
    "Punjabi Heritage and Culture by Saath": {
      "category": "In-person",
      "count": 95
    },
    "Pysanky Egg Painting": {
      "category": "UNKNOWN",
      "count": 4
    },
    "Qawalli Night at The Beacon": {
      "category": "In-person",
      "count": 163
    },
    "Qigong and Tai Chi Mid Autumn Moon Festival": {
      "category": "In-person",
      "count": 71
    },
    "RISE": {
      "category": "In-person",
      "count": 24172
    },
    "Ramadan Pavillion": {
      "category": "In-person",
      "count": 251710
    },
    "Re:Born": {
      "category": "Exhibition",
      "count": 29
    },
    "Reggae & Brass": {
      "category": "UNKNOWN",
      "count": 215
    },
    "Requiem": {
      "category": "UNKNOWN",
      "count": 190
    },
    "Rich(ard) Dawson": {
      "category": "UNKNOWN",
      "count": 187
    },
    "Richard Hawley / Black Dyke Band": {
      "category": "UNKNOWN",
      "count": 1442
    },
    "Rizwan-Muazzam Qawwali Group": {
      "category": "UNKNOWN",
      "count": 610
    },
    "Robyn Hood": {
      "category": "In-person",
      "count": 164
    },
    "Roshni": {
      "category": "In-person",
      "count": 104
    },
    "STATUESQUE by Naomi Parker and Chicks on Sticks": {
      "category": "In-person",
      "count": 4624
    },
    "STRIKE": {
      "category": "In-person",
      "count": 950
    },
    "Say It As It Is (Bowling)": {
      "category": "In-person",
      "count": 40
    },
    "Say It As It Is (Cliffe Castle)": {
      "category": "In-person",
      "count": 59
    },
    "Say It As It Is (Wibsey)": {
      "category": "In-person",
      "count": 119
    },
    "Self Taping & Audition Techniques": {
      "category": "UNKNOWN",
      "count": 25
    },
    "Simon Boccanegra": {
      "category": "In-person",
      "count": 1681
    },
    "Sing, Dance, Leap": {
      "category": "In-person",
      "count": 2100
    },
    "Sip and Paint with Creative Flare": {
      "category": "In-person",
      "count": 49
    },
    "Sisters 360": {
      "category": "In-person",
      "count": 146
    },
    "Sisterverse Poetry Night": {
      "category": "UNKNOWN",
      "count": 45
    },
    "Sonic Swirls and Silence (BD: is LIT)": {
      "category": "Exhibition",
      "count": 1812
    },
    "Spin Arts: RIDE": {
      "category": "In-person",
      "count": 366
    },
    "Sponsorship - Alhambra Philanthropy": {
      "category": "In-person",
      "count": 25
    },
    "Sponsorship - Bradford Means Business": {
      "category": "In-person",
      "count": 500
    },
    "Sponsorship - Business Breakfast": {
      "category": "In-person",
      "count": 35
    },
    "Sponsorship - High Sheriff": {
      "category": "In-person",
      "count": 280
    },
    "Sponsorship - Insider Placemaking": {
      "category": "In-person",
      "count": 125
    },
    "Sponsorship - Loading Bay Funder": {
      "category": "In-person",
      "count": 27
    },
    "Sponsorship - Northern Trains": {
      "category": "In-person",
      "count": 40
    },
    "Sponsorship - Sports Awards": {
      "category": "In-person",
      "count": 400
    },
    "Sponsorship - Super Soapbox Challenge": {
      "category": "In-person",
      "count": 20000
    },
    "Sponsorship - YABA": {
      "category": "In-person",
      "count": 210
    },
    "Sponsorship - Yorkshire Water": {
      "category": "In-person",
      "count": 35
    },
    "Steven Frayne: Back Home and Magical": {
      "category": "In-person",
      "count": 1825
    },
    "Street Choirs Festival": {
      "category": "In-person",
      "count": 800
    },
    "Sudha Bhuchar residency Theatre in the Mill": {
      "category": "In-person",
      "count": 233
    },
    "Summer Solstice Solace": {
      "category": "UNKNOWN",
      "count": 27
    },
    "Summer Sounds - Day 1": {
      "category": "Festival",
      "count": 251
    },
    "Summer Sounds - Day 2": {
      "category": "Festival",
      "count": 288
    },
    "Summer of Song with Steeton Male Voice Choir": {
      "category": "In-person",
      "count": 133
    },
    "Surprise Creatures - Drawing Together!": {
      "category": "UNKNOWN",
      "count": 24
    },
    "Sustainability Panel: Future": {
      "category": "UNKNOWN",
      "count": 22
    },
    "Sustainability Panel: Shadows and Light": {
      "category": "UNKNOWN",
      "count": 30
    },
    "Sustainability Panel: The Present": {
      "category": "UNKNOWN",
      "count": 41
    },
    "Sustenance the Power of Food": {
      "category": "In-person",
      "count": 24
    },
    "Tape Letters": {
      "category": "Exhibition",
      "count": 753
    },
    "Tech Styles @ The Beacon": {
      "category": "In-person",
      "count": 318
    },
    "Teen Scene Party": {
      "category": "In-person",
      "count": 361
    },
    "Tent of Hope": {
      "category": "In-person",
      "count": 400
    },
    "Testo": {
      "category": "In-person",
      "count": 209
    },
    "Thar Farraige (Over Sea)": {
      "category": "UNKNOWN",
      "count": 214
    },
    "The 56": {
      "category": "In-person",
      "count": 164
    },
    "The Archers Podcast Recording": {
      "category": "UNKNOWN",
      "count": 327
    },
    "The Belgrave House Band - Back to Black": {
      "category": "In-person",
      "count": 140
    },
    "The Bradford Progress": {
      "category": "In-person",
      "count": 10668
    },
    "The Dreams I Had: Andrea Dunbar": {
      "category": "In-person",
      "count": 979
    },
    "The Empty Chair with Alive & Kicking ": {
      "category": "UNKNOWN",
      "count": 39
    },
    "The Invite by Mind the Gap": {
      "category": "In-person",
      "count": 304
    },
    "The Pahari-Pothwari Literature Project Showcase": {
      "category": "UNKNOWN",
      "count": 203
    },
    "The Pahari-Pothwari Literature Project by Nabeela Ahmed": {
      "category": "In-person",
      "count": 160
    },
    "The Path": {
      "category": "UNKNOWN",
      "count": 662
    },
    "The Railway Children": {
      "category": "In-person",
      "count": 2038
    },
    "The Sticky Dance": {
      "category": "In-person",
      "count": 50
    },
    "The Tiger Lillies": {
      "category": "In-person",
      "count": 149
    },
    "The Verb": {
      "category": "UNKNOWN",
      "count": 309
    },
    "Threads of Sound: A Woollen Heritage": {
      "category": "UNKNOWN",
      "count": 260
    },
    "Tower of Now": {
      "category": "In-person",
      "count": 300000
    },
    "Tower of Now (capital project)": {
      "category": "In-person",
      "count": 299999
    },
    "Toxic": {
      "category": "In-person",
      "count": 165
    },
    "Traditional Ukrainian Painting": {
      "category": "UNKNOWN",
      "count": 9
    },
    "Tu i Tam / Tyt i Tam": {
      "category": "Exhibition",
      "count": 1628
    },
    "Turner Prize": {
      "category": "Exhibition, In-person",
      "count": 27569
    },
    "University of Bradford Programme": {
      "category": "In-person",
      "count": 338
    },
    "Unspun Stories": {
      "category": "Exhibition",
      "count": 1852
    },
    "Urooj Ashfaq: How To Be A Baddie": {
      "category": "In-person",
      "count": 173
    },
    "Voice Notes": {
      "category": "UNKNOWN",
      "count": 182
    },
    "Voices in Action: Creating Characters & Writing Dialogue": {
      "category": "UNKNOWN",
      "count": 13
    },
    "WOW Community Partnership": {
      "category": "In-person",
      "count": 159
    },
    "Wallace & Gromit: The Wrong Trousers - Live": {
      "category": "UNKNOWN",
      "count": 571
    },
    "Wandering Imaginations": {
      "category": "Exhibition, In-person",
      "count": 1060
    },
    "We Are Still Asafo": {
      "category": "In-person",
      "count": 387
    },
    "We Will Sing by Ann Hamilton at Salt's Mill": {
      "category": "Exhibition",
      "count": 33443
    },
    "West Yorkshire Young Poet Laureate": {
      "category": "In-person",
      "count": 109
    },
    "Whale, Where Are You Going?": {
      "category": "In-person",
      "count": 167
    },
    "What Are You Watching?": {
      "category": "UNKNOWN",
      "count": 45
    },
    "Where It Began \u2013 Osman Yousefzada": {
      "category": "Exhibition",
      "count": 468490
    },
    "Whine List": {
      "category": "In-person",
      "count": 124
    },
    "Wild Uplands": {
      "category": "Exhibition, In-person",
      "count": 70997
    },
    "Wonky Olympics": {
      "category": "In-person",
      "count": 44
    },
    "Word Out Sharing Event": {
      "category": "UNKNOWN",
      "count": 19
    },
    "Words First Showcase": {
      "category": "UNKNOWN",
      "count": 141
    },
    "World Curry Festival": {
      "category": "In-person",
      "count": 109
    },
    "World of Women (Cecil Green Arts)": {
      "category": "In-person",
      "count": 548
    },
    "YOU:MATTER": {
      "category": "Exhibition",
      "count": 40865
    },
    "Yearn - Sipho": {
      "category": "UNKNOWN",
      "count": 292
    },
    "Yoga & Poetry Workshop": {
      "category": "UNKNOWN",
      "count": 15
    },
    "Your Best Guess": {
      "category": "In-person",
      "count": 52
    },
    "Youth Fest 25": {
      "category": "In-person",
      "count": 177
    },
    "Youthology": {
      "category": "In-person",
      "count": 171
    },
    "Zee and the City": {
      "category": "In-person",
      "count": 5151
    },
    "asses.masses": {
      "category": "In-person",
      "count": 82
    }
  },
  "ticketed": {
    "sold": {
      "total": 169273,
      "bradford": 65536,
      "by_project": {
        "'Creative Thinkers' in Your Classroom": 81,
        "A Somali Village in Lister Park: Friends of Bradford Art Galleries and Museums": 155,
        "A World Without Death": 792,
        "Alfred Bradley Bursary Award (ABBA)": 55,
        "An Evening with The Beehive Poets: Poetry Playground": 36,
        "An Evening with: Jacqui Dankworth": 179,
        "Ang\u00e9lique Kidjo: African Symphony": 1341,
        "Antony Szmierek": 387,
        "Ark Bradford: Storm Gathering": 122,
        "BBC Introducing @ The Beacon": 174,
        "BBC Introducing Panel": 44,
        "BBC Introducing Showcase": 214,
        "BBC Introducing at The Underground": 139,
        "BBC Radio 4 Beyond Belief": 129,
        "BBC Radio 4 Front Row": 388,
        "BBC Radio 4 Loose Ends": 836,
        "BBC Radio 4 Start the Week": 171,
        "BBC Radio 4 The Adverb": 299,
        "BBC Radio Club": 86,
        "BBC Writers: Who We Are & What We Do": 59,
        "BOLD! Bradford Artist Scratch Night": 48,
        "Babysphere & Colorsphere": 748,
        "Back in The Pink: Big Nights OUT": 51,
        "Back in The Pink: Cinema Special": 34,
        "Back in The Pink: LGBTQ+ History Walking Tour": 30,
        "Back in the Pink: Pink After Dark": 145,
        "Bantam's Drift": 135,
        "Bassline Symphony": 1443,
        "Beacon": 681,
        "Big Bradford WESTival Celebration of Culture and Community": 192,
        "Big Quiffy Bingo": 93,
        "Blankets & Wine Festival Bradford": 1534,
        "Bloom": 6967,
        "Book Making": 3,
        "Book of Bradford Launch": 135,
        "Bradford Glow": 274,
        "Bradford Made": 242,
        "Bradford Open Mic Night": 61,
        "Bradford on Foot": 83,
        "Brass on a Sunday Afternoon ": 227,
        "Built By Sound (formerly Daytimers)": 441,
        "CANCELLED Stick in the Wheel": 1,
        "CBeebies Bedtime Story Day": 1362,
        "CSL Poetry Gala: Part I": 170,
        "CSL Poetry Gala: Part II": 183,
        "CSL Poetry Shorts: Love in the 21st Century": 67,
        "CSL Poetry Shorts: Migration & Belonging": 65,
        "CSL Poetry Shorts: Mills & Hills": 58,
        "CSL Poetry Shorts: Mind & Body": 68,
        "CSL Poetry Shorts: Music & Lyrics": 68,
        "CSL Poetry Shorts: Poetic Justice": 69,
        "CSL Poetry Shorts: The Power of the Women of Bradford": 62,
        "CSL Poetry Shorts: Words in the Wild": 65,
        "Camille O'Sullivan": 190,
        "Charlotte Bront\u00eb: Senseless Trash": 29,
        "Chasing Sunlight": 267,
        "Chasing the Wind": 123,
        "Claytime": 227,
        "Cocoa Butter Club": 45,
        "Come Rest in Chaos": 54,
        "Common/Wealth: Public Interest": 1124,
        "Cool Runnings": 164,
        "Creative Careers Festival": 49,
        "Crepe Paper Flower-Making": 1,
        "Curious Investigators": 302,
        "DANCE SUITE": 257,
        "DJ Marco - Balkan Beats & Brass": 197,
        "Dancing with Colours": 55,
        "Dhamaal \u2013 Core": 258,
        "Dracula": 791,
        "Drag-Ford: Pre-Show Workshop": 18,
        "Drag-ford: Drag Cabaret Built in Bradford": 70,
        "Earth & Sky (part of Wild Uplands)": 139,
        "Echoes of the North": 271,
        "Eggs Collective Dark Nights": 235,
        "Eliza Carthy": 197,
        "Elmet": 1944,
        "Embedding the Arts in Your School": 19,
        "Evening Conversations": 162,
        "Everything for Everyone": 195,
        "Film: Amar Akbar Anthony": 63,
        "Film: Bajrangi Bhaijaan": 22,
        "Film: Barbie": 127,
        "Film: Big Hero 6": 140,
        "Film: Bride and Prejudice": 48,
        "Film: Conclave": 129,
        "Film: Dil Dhadakne Do": 11,
        "Film: Everybody's Talking About Jamie": 410,
        "Film: Everything Everywhere All at Once": 96,
        "Film: Fantastic Mr. Fox": 109,
        "Film: Flow": 272,
        "Film: Jab We Met": 126,
        "Film: Pulp Fiction": 50,
        "Film: Sexy Beast": 374,
        "Film: Speed": 95,
        "Film: The Apartment": 9,
        "Film: The Apartment ": 11,
        "Film: The Grand Budapest Hotel": 384,
        "Film: The Greatest Showman": 205,
        "Film: The Lorax": 177,
        "Film: The Matrix": 101,
        "Film: The Terminator": 35,
        "Film: The Wild Robot": 75,
        "Film: Zindagi Na Milegi Dobara": 39,
        "Forward Prize Launch": 83,
        "Gaana Shaana - Open Mic": 51,
        "Get Seen, Get Hired: Build a Creative Career Online": 30,
        "Ginger Johnson's Fun House": 197,
        "Greed": 35,
        "Grue Audio Description - Penfriend Kit": 39,
        "Hall Royd Brass Band": 227,
        "Happy Hype": 47,
        "Holocene": 356,
        "Hot Caribbean Beatz in the Park": 225,
        "How to Get Published": 196,
        "Imaginary Friends": 49,
        "In Conversation with Ann Hamilton and Guests": 97,
        "Into the Night": 643,
        "Intro to Comedy Workshop Series with Alex Dunlop": 10,
        "It's Your Round": 113,
        "KOKOROKO": 1170,
        "Kailey": 271,
        "Khooghi": 198,
        "La Haine - Asian Dub Foundation": 1144,
        "Lady Maisery / O'Hooley & Tidow": 202,
        "Language is a Queer Thing Showcase": 112,
        "Language is a Queer Thing Workshop": 15,
        "Language: no broblem": 133,
        "Lanre Bakare - 'We Were There' Book Launch": 198,
        "Last Rites": 110,
        "Lay Down Your Burdens": 192,
        "Leeds Young Film Festival: INDIs Filmmaker Award": 57,
        "Les Enfants Terribles - A Gameshow for Awful Children": 193,
        "Life Class (509 Arts)": 1264,
        "Life Class: Cuppa T": 77,
        "Lighthouse": 656,
        "Listen In: Jeremy Dyson & Mark Gatiss": 965,
        "Listen In: Nick Ahad": 87,
        "Little Wimmin": 316,
        "Loaded Laughs (#1)": 684,
        "Love. Unite. Freedom": 185,
        "MARCH": 233,
        "Mercury Songs": 290,
        "Moth x Human": 235,
        "Museums for Play and Growth": 122,
        "My Thousand Year Old Land": 73,
        "Nocturnal Sun": 182,
        "North Street Band": 82,
        "N\u2019dehou": 226,
        "OFMS: John Grant @ St Georges Hall": 734,
        "OFMS: Nadine Shah @ St. Georges Hall": 659,
        "Open-Air Cinema: Milner Field": 237,
        "Oranje Brass \u2013 Amazing Music From The Netherlands": 187,
        "Otherhood by Old Bird (Deborah Pakkar-Hull and Emma Adams)": 209,
        "Our Story": 108,
        "PLAY: Grue": 2205,
        "PLAY: REPLAY": 6178,
        "PLAY: The Great Adventure Build - Community Slots": 128,
        "PLAY: The Great Adventure Build - Home Education": 54,
        "PLAY: The Great Adventure Build - Schools": 128,
        "PLAY: The Great Adventure Build with Woodland Tribe": 2146,
        "Palettes": 384,
        "Palingenesis": 94,
        "Penguin": 253,
        "Penumbra": 182,
        "Peregrinations: Urban Nature Poetry Walk": 31,
        "Pins For Peace by Mek Summat": 215,
        "Pop Up Family Pride": 732,
        "Public Interest Club Night": 53,
        "Public Interest: Access Opening Event": 3,
        "Pysanky Egg Painting": 4,
        "Qawalli Night at The Beacon": 200,
        "Qigong and Tai Chi Mid Autumn Moon Festival": 71,
        "RISE": 23635,
        "Re:Born": 77,
        "Reggae & Brass": 215,
        "Requiem": 190,
        "Rich(ard) Dawson": 187,
        "Richard Hawley / Black Dyke Band": 1442,
        "Rizwan-Muazzam Qawwali Group": 610,
        "Robyn Hood": 178,
        "Roshni": 137,
        "Say It As It Is (Wibsey)": 281,
        "Self Taping & Audition Techniques": 25,
        "Sip and Paint with Creative Flare": 49,
        "Sisters 360": 179,
        "Sisterverse Poetry Night": 45,
        "Steven Frayne: Back Home and Magical": 1638,
        "Summer Solstice Solace": 27,
        "Summer Sounds - Day 1": 767,
        "Summer of Song with Steeton Male Voice Choir": 176,
        "Surprise Creatures - Drawing Together!": 24,
        "Sustainability Panel: Future": 22,
        "Sustainability Panel: Shadows and Light": 30,
        "Sustainability Panel: The Present": 41,
        "Tent of Hope": 232,
        "Testo": 252,
        "Thar Farraige (Over Sea)": 214,
        "The 56": 197,
        "The Archers Podcast Recording": 327,
        "The Belgrave House Band - Back to Black": 173,
        "The Dreams I Had: Andrea Dunbar": 979,
        "The Empty Chair with Alive & Kicking ": 39,
        "The Invite by Mind the Gap": 440,
        "The Pahari-Pothwari Literature Project Showcase": 203,
        "The Path": 662,
        "The Railway Children": 30464,
        "The Sticky Dance": 68,
        "The Tiger Lillies": 189,
        "The Verb": 309,
        "Threads of Sound: A Woollen Heritage": 260,
        "Toxic": 199,
        "Traditional Ukrainian Painting": 9,
        "Turner Prize": 42318,
        "Urooj Ashfaq: How To Be A Baddie": 186,
        "Voice Notes": 182,
        "Voices in Action: Creating Characters & Writing Dialogue": 13,
        "WE ARE STILL ASAFO": 506,
        "Wallace & Gromit: The Wrong Trousers - Live": 571,
        "Whale, Where Are You Going?": 205,
        "What Are You Watching?": 45,
        "Whine List": 145,
        "Wild Uplands": 15,
        "Word Out Sharing Event": 19,
        "Words First Showcase": 141,
        "Yearn - Sipho": 292,
        "Yoga & Poetry Workshop": 15,
        "Your Best Guess": 69,
        "asses.masses": 112
      },
      "by_geo": {
        "E06000001": 23,
        "E06000002": 31,
        "E06000003": 45,
        "E06000004": 83,
        "E06000005": 67,
        "E06000006": 30,
        "E06000007": 73,
        "E06000008": 82,
        "E06000009": 36,
        "E06000010": 379,
        "E06000011": 558,
        "E06000012": 67,
        "E06000013": 144,
        "E06000014": 1306,
        "E06000015": 67,
        "E06000016": 70,
        "E06000017": 19,
        "E06000018": 116,
        "E06000019": 10,
        "E06000020": 20,
        "E06000021": 23,
        "E06000022": 13,
        "E06000023": 66,
        "E06000024": 17,
        "E06000025": 19,
        "E06000026": 15,
        "E06000027": 4,
        "E06000030": 17,
        "E06000031": 10,
        "E06000032": 6,
        "E06000033": 21,
        "E06000034": 8,
        "E06000035": 11,
        "E06000036": 13,
        "E06000037": 9,
        "E06000038": 6,
        "E06000039": 2,
        "E06000040": 16,
        "E06000041": 26,
        "E06000042": 14,
        "E06000043": 41,
        "E06000044": 22,
        "E06000046": 11,
        "E06000047": 97,
        "E06000049": 217,
        "E06000050": 169,
        "E06000051": 60,
        "E06000052": 15,
        "E06000054": 43,
        "E06000055": 20,
        "E06000056": 32,
        "E06000057": 67,
        "E06000058": 24,
        "E06000059": 25,
        "E06000060": 65,
        "E06000061": 49,
        "E06000062": 46,
        "E06000063": 112,
        "E06000064": 222,
        "E06000065": 5612,
        "E06000066": 47,
        "E07000008": 62,
        "E07000009": 22,
        "E07000010": 3,
        "E07000011": 48,
        "E07000012": 28,
        "E07000032": 60,
        "E07000033": 23,
        "E07000034": 62,
        "E07000035": 94,
        "E07000036": 16,
        "E07000037": 119,
        "E07000038": 104,
        "E07000039": 43,
        "E07000040": 10,
        "E07000041": 15,
        "E07000042": 7,
        "E07000043": 2,
        "E07000044": 3,
        "E07000061": 2,
        "E07000062": 30,
        "E07000063": 2,
        "E07000064": 8,
        "E07000065": 20,
        "E07000066": 2,
        "E07000067": 10,
        "E07000068": 6,
        "E07000070": 15,
        "E07000071": 22,
        "E07000072": 30,
        "E07000073": 2,
        "E07000074": 5,
        "E07000075": 2,
        "E07000076": 13,
        "E07000077": 14,
        "E07000078": 25,
        "E07000079": 7,
        "E07000080": 2,
        "E07000081": 9,
        "E07000082": 16,
        "E07000083": 7,
        "E07000084": 10,
        "E07000085": 33,
        "E07000086": 6,
        "E07000087": 4,
        "E07000088": 4,
        "E07000089": 4,
        "E07000090": 2,
        "E07000091": 7,
        "E07000092": 3,
        "E07000093": 8,
        "E07000094": 13,
        "E07000095": 1,
        "E07000096": 20,
        "E07000099": 30,
        "E07000102": 8,
        "E07000103": 7,
        "E07000105": 7,
        "E07000106": 38,
        "E07000107": 2,
        "E07000108": 11,
        "E07000109": 4,
        "E07000110": 13,
        "E07000111": 19,
        "E07000112": 9,
        "E07000113": 6,
        "E07000114": 7,
        "E07000115": 9,
        "E07000116": 18,
        "E07000117": 85,
        "E07000118": 81,
        "E07000119": 37,
        "E07000120": 83,
        "E07000121": 152,
        "E07000122": 317,
        "E07000123": 73,
        "E07000124": 177,
        "E07000125": 86,
        "E07000126": 66,
        "E07000127": 51,
        "E07000128": 50,
        "E07000129": 8,
        "E07000130": 61,
        "E07000131": 33,
        "E07000132": 26,
        "E07000133": 6,
        "E07000134": 8,
        "E07000135": 6,
        "E07000136": 4,
        "E07000137": 33,
        "E07000138": 29,
        "E07000139": 31,
        "E07000140": 15,
        "E07000141": 30,
        "E07000142": 48,
        "E07000143": 10,
        "E07000144": 8,
        "E07000145": 6,
        "E07000146": 7,
        "E07000147": 6,
        "E07000148": 24,
        "E07000149": 20,
        "E07000170": 23,
        "E07000171": 89,
        "E07000172": 24,
        "E07000173": 48,
        "E07000174": 17,
        "E07000175": 60,
        "E07000176": 63,
        "E07000177": 21,
        "E07000178": 31,
        "E07000179": 35,
        "E07000180": 34,
        "E07000181": 14,
        "E07000192": 2,
        "E07000193": 21,
        "E07000194": 14,
        "E07000195": 15,
        "E07000196": 15,
        "E07000197": 27,
        "E07000198": 25,
        "E07000199": 1,
        "E07000200": 4,
        "E07000202": 22,
        "E07000203": 3,
        "E07000207": 18,
        "E07000208": 6,
        "E07000209": 18,
        "E07000210": 22,
        "E07000211": 6,
        "E07000212": 2,
        "E07000213": 13,
        "E07000214": 11,
        "E07000215": 19,
        "E07000216": 30,
        "E07000217": 8,
        "E07000218": 3,
        "E07000219": 22,
        "E07000220": 40,
        "E07000221": 39,
        "E07000222": 48,
        "E07000223": 5,
        "E07000224": 6,
        "E07000225": 15,
        "E07000226": 2,
        "E07000227": 19,
        "E07000228": 6,
        "E07000229": 13,
        "E07000234": 28,
        "E07000235": 6,
        "E07000236": 6,
        "E07000237": 9,
        "E07000238": 12,
        "E07000239": 8,
        "E07000240": 45,
        "E07000241": 22,
        "E07000242": 25,
        "E07000244": 73,
        "E07000245": 14,
        "E08000001": 129,
        "E08000002": 434,
        "E08000003": 814,
        "E08000004": 191,
        "E08000005": 199,
        "E08000006": 117,
        "E08000007": 264,
        "E08000008": 175,
        "E08000009": 311,
        "E08000010": 102,
        "E08000011": 10,
        "E08000012": 257,
        "E08000013": 44,
        "E08000014": 122,
        "E08000015": 98,
        "E08000016": 340,
        "E08000017": 290,
        "E08000018": 391,
        "E08000019": 1172,
        "E08000021": 96,
        "E08000022": 65,
        "E08000023": 2,
        "E08000024": 32,
        "E08000025": 139,
        "E08000026": 69,
        "E08000027": 38,
        "E08000028": 14,
        "E08000029": 33,
        "E08000030": 10,
        "E08000031": 15,
        "E08000032": 65536,
        "E08000033": 6674,
        "E08000034": 4695,
        "E08000035": 14323,
        "E08000036": 1133,
        "E08000037": 46,
        "E09000001": 2,
        "E09000002": 4,
        "E09000003": 36,
        "E09000004": 17,
        "E09000005": 20,
        "E09000006": 34,
        "E09000007": 54,
        "E09000008": 43,
        "E09000009": 72,
        "E09000010": 30,
        "E09000011": 45,
        "E09000012": 94,
        "E09000013": 23,
        "E09000014": 90,
        "E09000015": 17,
        "E09000016": 6,
        "E09000017": 14,
        "E09000018": 10,
        "E09000019": 43,
        "E09000020": 34,
        "E09000021": 14,
        "E09000022": 67,
        "E09000023": 59,
        "E09000024": 16,
        "E09000025": 13,
        "E09000026": 37,
        "E09000027": 33,
        "E09000028": 228,
        "E09000029": 14,
        "E09000030": 42,
        "E09000031": 46,
        "E09000032": 63,
        "E09000033": 32,
        "MISSING": 53401,
        "N09000001": 4,
        "N09000002": 1,
        "N09000003": 17,
        "N09000005": 7,
        "N09000006": 2,
        "N09000007": 7,
        "N09000008": 9,
        "N09000011": 21,
        "S12000005": 6,
        "S12000006": 7,
        "S12000008": 1,
        "S12000010": 25,
        "S12000011": 5,
        "S12000013": 3,
        "S12000014": 10,
        "S12000017": 31,
        "S12000018": 7,
        "S12000019": 6,
        "S12000020": 6,
        "S12000021": 5,
        "S12000023": 3,
        "S12000026": 13,
        "S12000028": 2,
        "S12000029": 12,
        "S12000030": 4,
        "S12000033": 17,
        "S12000034": 8,
        "S12000036": 173,
        "S12000038": 5,
        "S12000039": 1,
        "S12000040": 2,
        "S12000041": 6,
        "S12000042": 7,
        "S12000045": 7,
        "S12000047": 12,
        "S12000048": 15,
        "S12000049": 129,
        "S12000050": 14,
        "UNMATCHED": 528,
        "W06000001": 15,
        "W06000002": 29,
        "W06000003": 38,
        "W06000004": 17,
        "W06000005": 22,
        "W06000006": 21,
        "W06000008": 6,
        "W06000009": 2,
        "W06000011": 15,
        "W06000012": 10,
        "W06000013": 3,
        "W06000014": 9,
        "W06000015": 49,
        "W06000016": 7,
        "W06000018": 5,
        "W06000020": 2,
        "W06000021": 15,
        "W06000022": 10,
        "W06000023": 12
      }
    },
    "scanned": {
      "total": {
        "sold": 47112,
        "scanned": 17396
      }
    }
  },
  "unticketed": null
}