{
  "total": 2134,
  "free": 1128,
  "by_category": {
    "Digital": 3,
    "Exhibition": 690,
    "Festival": 55,
    "Film": 403,
    "In-person": 962,
    "Training and skills development": 21
  },
  "by_project": {
    "A Good Yarn": {
      "category": "Exhibition",
      "count": 57
    },
    "A Good Yarn: Luke Jerram": {
      "category": "In-person",
      "count": 3
    },
    "A Screen Near You - The Collective View (film societies support)": {
      "category": "Film",
      "count": 4
    },
    "A Somali Village in Lister Park: Friends of Bradford Art Galleries and Museums": {
      "category": "In-person",
      "count": 1
    },
    "A World Without Death": {
      "category": "In-person",
      "count": 3
    },
    "Akram Khan and Dance United - Memories of the Future": {
      "category": "In-person",
      "count": 1
    },
    "Ark": {
      "category": "In-person",
      "count": 21
    },
    "Art & Play Family Day": {
      "category": "In-person",
      "count": 1
    },
    "BBC Contains Strong Language": {
      "category": "Festival",
      "count": 44
    },
    "BBC Introducing at The Underground": {
      "category": "In-person",
      "count": 1
    },
    "BD: Walls": {
      "category": "In-person",
      "count": 4
    },
    "BOLD! Bradford Artist Scratch Night": {
      "category": "In-person",
      "count": 1
    },
    "Babysphere & Colorsphere": {
      "category": "In-person",
      "count": 5
    },
    "Baton of Hope": {
      "category": "In-person",
      "count": 2
    },
    "Beacon": {
      "category": "In-person",
      "count": 2
    },
    "Big Bradford WESTival Celebration of Culture and Community": {
      "category": "In-person",
      "count": 1
    },
    "Big Screen - Ilkley Lido": {
      "category": "Film",
      "count": 2
    },
    "Big Screen - Thornton Viaduct": {
      "category": "Film",
      "count": 1
    },
    "Blankets & Wine Festival Bradford": {
      "category": "In-person",
      "count": 1
    },
    "Bloom": {
      "category": "In-person",
      "count": 42
    },
    "Bradford 2025 Website": {
      "category": "Digital",
      "count": 0
    },
    "Bradford Glow": {
      "category": "Digital",
      "count": 0
    },
    "Bradford Literature Festival @ Loading Bay": {
      "category": "In-person",
      "count": 1
    },
    "Bradford Made": {
      "category": "In-person",
      "count": 3
    },
    "Bradford On Foot": {
      "category": "Digital",
      "count": 0
    },
    "Bradford Producing Hub": {
      "category": "Training and skills development",
      "count": 21
    },
    "Bradford South Asian Festival : Shadmanny": {
      "category": "In-person",
      "count": 1
    },
    "Bradford StoryHub Drop In": {
      "category": "In-person",
      "count": 2
    },
    "Bradford on Foot": {
      "category": "In-person",
      "count": 6
    },
    "Bradford's Bigger Picture - Film Festivals support": {
      "category": "Film",
      "count": 1
    },
    "Bradford: A City of Film": {
      "category": "Film",
      "count": 4
    },
    "CANCELLED Stick in the Wheel": {
      "category": "In-person",
      "count": 1
    },
    "CHANNELS": {
      "category": "Digital",
      "count": 0
    },
    "Camille O'Sullivan": {
      "category": "In-person",
      "count": 1
    },
    "Chasing the Wind": {
      "category": "In-person",
      "count": 4
    },
    "Cliffe Castle Park 75th Birthday Bash": {
      "category": "In-person",
      "count": 1
    },
    "Closing Event (Brighter Still) - Emily Lim/Dan Canham": {
      "category": "In-person",
      "count": 3
    },
    "Cocoa Butter Club": {
      "category": "In-person",
      "count": 2
    },
    "Come Rest in Chaos": {
      "category": "In-person",
      "count": 1
    },
    "Compagnie Off: Giraffes": {
      "category": "In-person",
      "count": 1
    },
    "Creative Summer Social (Cultural Voice Forum)": {
      "category": "In-person",
      "count": 1
    },
    "Cultural Learning One-Off Activity": {
      "category": "In-person",
      "count": 1
    },
    "Cultural Learning Steering Group": {
      "category": "In-person",
      "count": 2
    },
    "Digital Map": {
      "category": "In-person",
      "count": 1
    },
    "Drag-ford: Drag Cabaret Built in Bradford": {
      "category": "In-person",
      "count": 2
    },
    "Eggs Collective Dark Nights": {
      "category": "In-person",
      "count": 1
    },
    "Elevate - Heritage Skills Project": {
      "category": "In-person",
      "count": 4
    },
    "Elmet": {
      "category": "In-person",
      "count": 3
    },
    "Endless Hum": {
      "category": "In-person",
      "count": 1
    },
    "Fair Play Symposium": {
      "category": "In-person",
      "count": 1
    },
    "Festival of Archaeology: Archaeology Talks!": {
      "category": "Festival",
      "count": 4
    },
    "Film Culture in Bradford and Keighley: Friends of Bradford Art Galleries and Museums": {
      "category": "In-person",
      "count": 1
    },
    "Four Nations Outdoor Arts Bursary 2025": {
      "category": "In-person",
      "count": 14
    },
    "Frontline 1984-1985 by Victor Wedderburn": {
      "category": "Exhibition",
      "count": 92
    },
    "Gaana Shaana - Open Mic": {
      "category": "In-person",
      "count": 1
    },
    "Great Crafty Get-Together": {
      "category": "In-person",
      "count": 1
    },
    "Green Family Creative Day": {
      "category": "In-person",
      "count": 1
    },
    "Health and Wellbeing Day": {
      "category": "In-person",
      "count": 1
    },
    "Here We Stand": {
      "category": "Exhibition",
      "count": 20
    },
    "Highfield South Asian Celebration": {
      "category": "In-person",
      "count": 1
    },
    "Hindu Sangh Culture Event": {
      "category": "In-person",
      "count": 1
    },
    "Hot Caribbean Beatz in the Park": {
      "category": "In-person",
      "count": 1
    },
    "Ice Age Art Now": {
      "category": "Exhibition",
      "count": 85
    },
    "Imaginary Friends": {
      "category": "In-person",
      "count": 1
    },
    "Intro to Comedy Workshop Series with Alex Dunlop": {
      "category": "In-person",
      "count": 3
    },
    "Jameel Prize: Moving Images": {
      "category": "Exhibition",
      "count": 42
    },
    "Journey's of Mai: Youth Engagement Programme": {
      "category": "Exhibition",
      "count": 6
    },
    "Journeys with Mai": {
      "category": "Exhibition",
      "count": 42
    },
    "Kailey": {
      "category": "In-person",
      "count": 5
    },
    "Khooghi": {
      "category": "In-person",
      "count": 3
    },
    "Last Rites": {
      "category": "In-person",
      "count": 1
    },
    "Learning resource downloads": {
      "category": "Digital",
      "count": 0
    },
    "Leeds School of Architecture x Bradford 2025 - The City As a Festival": {
      "category": "Exhibition",
      "count": 4
    },
    "Let's Make": {
      "category": "In-person",
      "count": 4
    },
    "Life Class (509 Arts)": {
      "category": "In-person",
      "count": 4
    },
    "Little Explorers [Festival of Archaeology]": {
      "category": "In-person",
      "count": 1
    },
    "Little Foodies": {
      "category": "In-person",
      "count": 1
    },
    "Loaded Laughs (#3)": {
      "category": "In-person",
      "count": 1
    },
    "Loud and Proud Dohl Drumming": {
      "category": "In-person",
      "count": 2
    },
    "Meet Our Mothers": {
      "category": "In-person",
      "count": 2
    },
    "Mega Drawing Box in the Park": {
      "category": "In-person",
      "count": 2
    },
    "Memories of the Future": {
      "category": "In-person",
      "count": 1
    },
    "My Thousand Year Old Land": {
      "category": "In-person",
      "count": 2
    },
    "National Saturday Club": {
      "category": "In-person",
      "count": 4
    },
    "Nationhood: Memory and Hope": {
      "category": "Exhibition",
      "count": 50
    },
    "New Focus: Bradford Young Curators": {
      "category": "Exhibition",
      "count": 27
    },
    "On Yer Bike": {
      "category": "Exhibition",
      "count": 5
    },
    "Opera North Earth and Sky": {
      "category": "Digital",
      "count": 3
    },
    "Our Patch": {
      "category": "In-person",
      "count": 496
    },
    "Our Story": {
      "category": "In-person",
      "count": 1
    },
    "Our Turn: Visual Arts Festival": {
      "category": "Exhibition",
      "count": 11
    },
    "PLAY Facilitators @ Beacon (all)": {
      "category": "In-person",
      "count": 7
    },
    "PLAY: Alive & Kicking Drama Adventures": {
      "category": "In-person",
      "count": 16
    },
    "PLAY: Intergenerational Play": {
      "category": "In-person",
      "count": 16
    },
    "PLAY: Island of Foam (WOW)": {
      "category": "In-person",
      "count": 2
    },
    "PLAY: Playable Commission": {
      "category": "In-person",
      "count": 3
    },
    "PLAY: REPLAY": {
      "category": "In-person",
      "count": 1
    },
    "PLAY: Science Explorers Play Lab": {
      "category": "In-person",
      "count": 5
    },
    "PLAY: The Great Adventure Build with Woodland Tribe": {
      "category": "In-person",
      "count": 28
    },
    "Palingenesis": {
      "category": "In-person",
      "count": 1
    },
    "Peace Picnics (all parks)": {
      "category": "In-person",
      "count": 2
    },
    "Penguin Books 16+ Panel": {
      "category": "In-person",
      "count": 2
    },
    "People First Keighley and Craven Summer Party": {
      "category": "In-person",
      "count": 1
    },
    "Pictureville Screenings": {
      "category": "Film",
      "count": 384
    },
    "Pictureville Screenings - Cine Spotlights": {
      "category": "Film",
      "count": 1
    },
    "Pictureville Screenings - Epic Yorkshire Season": {
      "category": "Film",
      "count": 1
    },
    "Pictureville Screenings - Film4 Curated Season": {
      "category": "Film",
      "count": 4
    },
    "Poetry Takeaway": {
      "category": "In-person",
      "count": 3
    },
    "Qigong and Tai Chi Mid Autumn Moon Festival": {
      "category": "In-person",
      "count": 1
    },
    "Re:Born": {
      "category": "Exhibition",
      "count": 3
    },
    "SBC Theatre": {
      "category": "In-person",
      "count": 4
    },
    "STRIKE": {
      "category": "In-person",
      "count": 35
    },
    "Say It As It Is (Cliffe Castle)": {
      "category": "In-person",
      "count": 1
    },
    "Share Your Story at Beacon (National Literacy Trust)": {
      "category": "In-person",
      "count": 7
    },
    "Share and Care (Bradford New Church, Frizinghall)": {
      "category": "In-person",
      "count": 1
    },
    "Sip and Paint with Creative Flare": {
      "category": "In-person",
      "count": 1
    },
    "So Far, So Good (Yorkshire Dance, as part of BD FEST)": {
      "category": "In-person",
      "count": 11
    },
    "Spin Arts: RIDE": {
      "category": "In-person",
      "count": 4
    },
    "Sudha Bhuchar residency Theatre in the Mill": {
      "category": "In-person",
      "count": 5
    },
    "Summer Sounds - Day 1": {
      "category": "Festival",
      "count": 1
    },
    "Summer Sounds - Day 2": {
      "category": "Festival",
      "count": 6
    },
    "Summer of Song with Steeton Male Voice Choir": {
      "category": "In-person",
      "count": 1
    },
    "Teen Scene Party": {
      "category": "In-person",
      "count": 1
    },
    "Tent of Hope": {
      "category": "In-person",
      "count": 11
    },
    "The Ceremony": {
      "category": "Film",
      "count": 1
    },
    "The Invite by Mind the Gap": {
      "category": "In-person",
      "count": 7
    },
    "The Railway Children": {
      "category": "In-person",
      "count": 63
    },
    "Tu i Tam / Tyt i Tam: Tim Smith & Lodz Fotofestival": {
      "category": "Exhibition",
      "count": 19
    },
    "Turner Prize": {
      "category": "Exhibition",
      "count": 26
    },
    "Wandering Imaginations: Emerging Fantasy Writer Exchange": {
      "category": "Exhibition",
      "count": 2
    },
    "We Will Sing by Ann Hamilton at Salt's Mill": {
      "category": "Exhibition",
      "count": 4
    },
    "Whale, Where Are You Going?": {
      "category": "In-person",
      "count": 1
    },
    "Where It Began \u2013 Osman Yousefzada": {
      "category": "Exhibition",
      "count": 92
    },
    "Wild Uplands": {
      "category": "Exhibition",
      "count": 12
    },
    "Wonky Olympics": {
      "category": "In-person",
      "count": 6
    },
    "World Curry Festival": {
      "category": "In-person",
      "count": 2
    },
    "World of Women (Cecil Green Arts)": {
      "category": "In-person",
      "count": 3
    },
    "YOU:MATTER": {
      "category": "Exhibition",
      "count": 91
    },
    "Your Best Guess": {
      "category": "In-person",
      "count": 2
    },
    "Youth Fest 25": {
      "category": "In-person",
      "count": 1
    },
    "Youth Pass Events": {
      "category": "In-person",
      "count": 8
    },
    "Zee and the City": {
      "category": "In-person",
      "count": 7
    },
    "to delete (was alam lohar workshop)": {
      "category": "In-person",
      "count": 1
    },
    "zz - Beacon - Non-project related venue activity": {
      "category": "In-person",
      "count": 2
    }
  },
  "by_ticketed": [
    {
      "ticketed": "No",
      "count": 997,
      "projects": [
        "A Good Yarn: Luke Jerram",
        "Ark",
        "Art & Play Family Day",
        "BBC Contains Strong Language",
        "Baton of Hope",
        "Bloom",
        "Bradford Made",
        "Bradford South Asian Festival : Shadmanny",
        "Bradford StoryHub Drop In",
        "Bradford on Foot",
        "Cliffe Castle Park 75th Birthday Bash",
        "Closing Event (Brighter Still) - Emily Lim/Dan Canham",
        "Compagnie Off: Giraffes",
        "Cultural Learning One-Off Activity",
        "Cultural Learning Steering Group",
        "Digital Map",
        "Elmet",
        "Four Nations Outdoor Arts Bursary 2025",
        "Frontline 1984-1985 by Victor Wedderburn",
        "Great Crafty Get-Together",
        "Green Family Creative Day",
        "Health and Wellbeing Day",
        "Here We Stand",
        "Highfield South Asian Celebration",
        "Journey's of Mai: Youth Engagement Programme",
        "Kailey",
        "Khooghi",
        "Leeds School of Architecture x Bradford 2025 - The City As a Festival",
        "Let's Make",
        "Little Explorers [Festival of Archaeology]",
        "Little Foodies",
        "Loud and Proud Dohl Drumming",
        "Meet Our Mothers",
        "Mega Drawing Box in the Park",
        "My Thousand Year Old Land",
        "National Saturday Club",
        "New Focus: Bradford Young Curators",
        "On Yer Bike",
        "Our Patch",
        "Our Turn: Visual Arts Festival",
        "PLAY Facilitators @ Beacon (all)",
        "PLAY: Alive & Kicking Drama Adventures",
        "PLAY: Intergenerational Play",
        "PLAY: Island of Foam (WOW)",
        "PLAY: Playable Commission",
        "PLAY: REPLAY",
        "PLAY: Science Explorers Play Lab",
        "Peace Picnics (all parks)",
        "Poetry Takeaway",
        "STRIKE",
        "Share Your Story at Beacon (National Literacy Trust)",
        "Share and Care (Bradford New Church, Frizinghall)",
        "So Far, So Good (Yorkshire Dance, as part of BD FEST)",
        "Spin Arts: RIDE",
        "Tent of Hope",
        "The Railway Children",
        "Tu i Tam / Tyt i Tam: Tim Smith & Lodz Fotofestival",
        "Turner Prize",
        "We Will Sing by Ann Hamilton at Salt's Mill",
        "Where It Began \u2013 Osman Yousefzada",
        "Wild Uplands",
        "Wonky Olympics",
        "World of Women (Cecil Green Arts)",
        "Zee and the City",
        "to delete (was alam lohar workshop)"
      ]
    },
    {
      "ticketed": "Unknown",
      "count": 863,
      "projects": [
        "A Good Yarn",
        "BBC Introducing at The Underground",
        "BD: Walls",
        "Beacon",
        "Bradford Made",
        "Bradford Producing Hub",
        "Bradford: A City of Film",
        "CANCELLED Stick in the Wheel",
        "CHANNELS",
        "Endless Hum",
        "Ice Age Art Now",
        "Jameel Prize: Moving Images",
        "Journey's of Mai: Youth Engagement Programme",
        "Journeys with Mai",
        "Memories of the Future",
        "Nationhood: Memory and Hope",
        "New Focus: Bradford Young Curators",
        "Opera North Earth and Sky",
        "Our Patch",
        "Our Turn: Visual Arts Festival",
        "PLAY: Science Explorers Play Lab",
        "Pictureville Screenings",
        "SBC Theatre",
        "STRIKE",
        "The Invite by Mind the Gap",
        "The Railway Children",
        "Tu i Tam / Tyt i Tam: Tim Smith & Lodz Fotofestival",
        "Turner Prize",
        "Wandering Imaginations: Emerging Fantasy Writer Exchange",
        "YOU:MATTER",
        "Youth Fest 25",
        "Zee and the City",
        "zz - Beacon - Non-project related venue activity"
      ]
    },
    {
      "ticketed": "Yes (Paid: Ticketed by Bradford 2025)",
      "count": 125,
      "projects": [
        "A World Without Death",
        "BOLD! Bradford Artist Scratch Night",
        "Babysphere & Colorsphere",
        "Big Bradford WESTival Celebration of Culture and Community",
        "Big Screen - Ilkley Lido",
        "Big Screen - Thornton Viaduct",
        "Bloom",
        "Camille O'Sullivan",
        "Chasing the Wind",
        "Cocoa Butter Club",
        "Come Rest in Chaos",
        "Drag-ford: Drag Cabaret Built in Bradford",
        "Eggs Collective Dark Nights",
        "Gaana Shaana - Open Mic",
        "Hot Caribbean Beatz in the Park",
        "Imaginary Friends",
        "Intro to Comedy Workshop Series with Alex Dunlop",
        "Kailey",
        "Khooghi",
        "Last Rites",
        "Life Class (509 Arts)",
        "Loaded Laughs (#3)",
        "My Thousand Year Old Land",
        "Our Story",
        "Palingenesis",
        "Qigong and Tai Chi Mid Autumn Moon Festival",
        "Re:Born",
        "Say It As It Is (Cliffe Castle)",
        "Sip and Paint with Creative Flare",
        "Spin Arts: RIDE",
        "Sudha Bhuchar residency Theatre in the Mill",
        "Summer Sounds - Day 1",
        "Summer Sounds - Day 2",
        "The Invite by Mind the Gap",
        "The Railway Children",
        "Whale, Where Are You Going?",
        "Wild Uplands",
        "Your Best Guess"
      ]
    },
    {
      "ticketed": "Yes (Free: Ticketed by Bradford 2025)",
      "count": 119,
      "projects": [
        "A Somali Village in Lister Park: Friends of Bradford Art Galleries and Museums",
        "Ark",
        "BBC Contains Strong Language",
        "Blankets & Wine Festival Bradford",
        "Creative Summer Social (Cultural Voice Forum)",
        "Elevate - Heritage Skills Project",
        "Film Culture in Bradford and Keighley: Friends of Bradford Art Galleries and Museums",
        "Four Nations Outdoor Arts Bursary 2025",
        "Intro to Comedy Workshop Series with Alex Dunlop",
        "Meet Our Mothers",
        "Mega Drawing Box in the Park",
        "Our Patch",
        "Our Turn: Visual Arts Festival",
        "PLAY: Playable Commission",
        "PLAY: Science Explorers Play Lab",
        "PLAY: The Great Adventure Build with Woodland Tribe",
        "Penguin Books 16+ Panel",
        "People First Keighley and Craven Summer Party",
        "Re:Born",
        "Summer of Song with Steeton Male Voice Choir",
        "Tent of Hope",
        "Turner Prize",
        "Wild Uplands",
        "Youth Pass Events"
      ]
    },
    {
      "ticketed": "Yes (Paid: Ticketed by partner)",
      "count": 18,
      "projects": [
        "A Screen Near You - The Collective View (film societies support)",
        "Akram Khan and Dance United - Memories of the Future",
        "Bradford Literature Festival @ Loading Bay",
        "Bradford's Bigger Picture - Film Festivals support",
        "Pictureville Screenings - Cine Spotlights",
        "Pictureville Screenings - Epic Yorkshire Season",
        "Pictureville Screenings - Film4 Curated Season",
        "Sudha Bhuchar residency Theatre in the Mill",
        "The Ceremony",
        "World Curry Festival"
      ]
    },
    {
      "ticketed": "Yes (Free: Ticketed by a partner)",
      "count": 12,
      "projects": [
        "Elevate - Heritage Skills Project",
        "Fair Play Symposium",
        "Festival of Archaeology: Archaeology Talks!",
        "Four Nations Outdoor Arts Bursary 2025",
        "Hindu Sangh Culture Event",
        "Teen Scene Party"
      ]
    }
  ]
}