{
  "total": 39056,
  "by_type": {
    "community_participants": {
      "count": 32331,
      "attendances": 34663,
      "instances": 49739,
      "by_project": {
        "A Good Yarn: Luke Jerram": {
          "count": 17,
          "attendances": 17,
          "instances": 17,
          "category": "In-person"
        },
        "All Ages Singing Workshop (Beacon)": {
          "count": 27,
          "attendances": 45,
          "instances": 45,
          "category": "In-person"
        },
        "Ark": {
          "count": 143,
          "attendances": 143,
          "instances": 143,
          "category": "In-person"
        },
        "Art & Play Family Day": {
          "count": 117,
          "attendances": 117,
          "instances": 117,
          "category": "In-person"
        },
        "Beacon DRAW!": {
          "count": 1558,
          "attendances": 1558,
          "instances": 1558,
          "category": "In-person"
        },
        "Bradford Made MASTER": {
          "count": 60,
          "attendances": 0,
          "instances": 60,
          "category": "In-person"
        },
        "Bradford South Asian Festival : Shadmanny": {
          "count": 447,
          "attendances": 447,
          "instances": 447,
          "category": "In-person"
        },
        "Bradford on Foot": {
          "count": 55,
          "attendances": 0,
          "instances": 218,
          "category": "In-person"
        },
        "Closing Event (Brighter Still) - Emily Lim/Dan Canham": {
          "count": 21,
          "attendances": 21,
          "instances": 21,
          "category": "In-person"
        },
        "Compagnie Off: Giraffes": {
          "count": 10,
          "attendances": 0,
          "instances": 10,
          "category": "In-person"
        },
        "Creative Summer Social (Cultural Voice Forum)": {
          "count": 441,
          "attendances": 441,
          "instances": 441,
          "category": "In-person"
        },
        "Drag-ford: Drag Cabaret Built in Bradford": {
          "count": 18,
          "attendances": 18,
          "instances": 18,
          "category": "In-person"
        },
        "Elevate - Heritage Skills Project": {
          "count": 12,
          "attendances": 12,
          "instances": 12,
          "category": "In-person"
        },
        "Elmet": {
          "count": 32,
          "attendances": 33,
          "instances": 33,
          "category": "In-person"
        },
        "Great Crafty Get-Together": {
          "count": 86,
          "attendances": 86,
          "instances": 86,
          "category": "In-person"
        },
        "Green Family Creative Day": {
          "count": 100,
          "attendances": 100,
          "instances": 100,
          "category": "In-person"
        },
        "Health and Wellbeing Day": {
          "count": 190,
          "attendances": 190,
          "instances": 190,
          "category": "In-person"
        },
        "Ice Age Art Now": {
          "count": 204,
          "attendances": 0,
          "instances": 204,
          "category": "Exhibition"
        },
        "Kailey": {
          "count": 38,
          "attendances": 38,
          "instances": 38,
          "category": "In-person"
        },
        "Let's Make": {
          "count": 677,
          "attendances": 677,
          "instances": 677,
          "category": "In-person"
        },
        "Life Class (509 Arts)": {
          "count": 35,
          "attendances": 35,
          "instances": 35,
          "category": "In-person"
        },
        "Little Explorers [Festival of Archaeology]": {
          "count": 220,
          "attendances": 220,
          "instances": 220,
          "category": "In-person"
        },
        "Little Foodies": {
          "count": 948,
          "attendances": 948,
          "instances": 948,
          "category": "In-person"
        },
        "Loud and Proud Dohl Drumming": {
          "count": 218,
          "attendances": 218,
          "instances": 218,
          "category": "In-person"
        },
        "Meet Our Mothers": {
          "count": 1464,
          "attendances": 1464,
          "instances": 1464,
          "category": "In-person"
        },
        "Mega Drawing Box in the Park": {
          "count": 441,
          "attendances": 441,
          "instances": 441,
          "category": "In-person"
        },
        "On Yer Bike": {
          "count": 364,
          "attendances": 364,
          "instances": 364,
          "category": "Exhibition"
        },
        "Our Patch": {
          "count": 3137,
          "attendances": 3137,
          "instances": 3137,
          "category": "In-person"
        },
        "Our Patch - ACT OUT!": {
          "count": 16,
          "attendances": 55,
          "instances": 55,
          "category": "In-person"
        },
        "Our Patch - Art Bike Project": {
          "count": 19,
          "attendances": 19,
          "instances": 19,
          "category": "In-person"
        },
        "Our Patch - BSL and Art/Hands that Speak / Open Hands": {
          "count": 73,
          "attendances": 128,
          "instances": 128,
          "category": "In-person"
        },
        "Our Patch - Bangladeshi Community Association (BCA)": {
          "count": 13,
          "attendances": 34,
          "instances": 34,
          "category": "In-person"
        },
        "Our Patch - Barkerend Family Hub Sensory Garden and Craft Group Project": {
          "count": 36,
          "attendances": 245,
          "instances": 282,
          "category": "In-person"
        },
        "Our Patch - Beacon Creative family sessions": {
          "count": 219,
          "attendances": 219,
          "instances": 219,
          "category": "In-person"
        },
        "Our Patch - Beacon Rugby Tots": {
          "count": 148,
          "attendances": 148,
          "instances": 148,
          "category": "In-person"
        },
        "Our Patch - Bingley Skate Park/Myrtle Park": {
          "count": 112,
          "attendances": 139,
          "instances": 233,
          "category": "In-person"
        },
        "Our Patch - Birdbox Project": {
          "count": 128,
          "attendances": 255,
          "instances": 361,
          "category": "In-person"
        },
        "Our Patch - Boxing for wellbeing Al Hira Mosque": {
          "count": 25,
          "attendances": 290,
          "instances": 290,
          "category": "In-person"
        },
        "Our Patch - Boxing for wellbeing Carlton Bolling School": {
          "count": 8,
          "attendances": 153,
          "instances": 153,
          "category": "In-person"
        },
        "Our Patch - Boxing for wellbeing Kirkgate Centre": {
          "count": 12,
          "attendances": 78,
          "instances": 78,
          "category": "In-person"
        },
        "Our Patch - Boxing for wellbeing Oneness Centre": {
          "count": 21,
          "attendances": 113,
          "instances": 113,
          "category": "In-person"
        },
        "Our Patch - Brackenhill Park Picasso Parks": {
          "count": 17,
          "attendances": 20,
          "instances": 20,
          "category": "In-person"
        },
        "Our Patch - Buttershaw Sandale Trust 'Youth Art'": {
          "count": 38,
          "attendances": 47,
          "instances": 47,
          "category": "In-person"
        },
        "Our Patch - Community Trips - Bradford East": {
          "count": 66,
          "attendances": 66,
          "instances": 136,
          "category": "In-person"
        },
        "Our Patch - Community Trips - Bradford South": {
          "count": 122,
          "attendances": 124,
          "instances": 128,
          "category": "In-person"
        },
        "Our Patch - Community Trips - Bradford West": {
          "count": 55,
          "attendances": 56,
          "instances": 106,
          "category": "In-person"
        },
        "Our Patch - Community Trips - Keighley & Ilkley": {
          "count": 155,
          "attendances": 159,
          "instances": 399,
          "category": "In-person"
        },
        "Our Patch - Community Trips - Shipley": {
          "count": 25,
          "attendances": 25,
          "instances": 75,
          "category": "In-person"
        },
        "Our Patch - Creative Flare Clayton": {
          "count": 1,
          "attendances": 26,
          "instances": 26,
          "category": "In-person"
        },
        "Our Patch - DRAW Tour Workshops: East": {
          "count": 226,
          "attendances": 226,
          "instances": 437,
          "category": "In-person"
        },
        "Our Patch - DRAW Tour Workshops: Keighley & Ilkley": {
          "count": 20,
          "attendances": 20,
          "instances": 40,
          "category": "In-person"
        },
        "Our Patch - DRAW Tour Workshops: Shipley": {
          "count": 243,
          "attendances": 243,
          "instances": 486,
          "category": "In-person"
        },
        "Our Patch - DRAW Tour Workshops: South": {
          "count": 34,
          "attendances": 34,
          "instances": 34,
          "category": "In-person"
        },
        "Our Patch - DRAW Tour Workshops: West": {
          "count": 55,
          "attendances": 55,
          "instances": 55,
          "category": "In-person"
        },
        "Our Patch - Delius School": {
          "count": 4,
          "attendances": 36,
          "instances": 36,
          "category": "In-person"
        },
        "Our Patch - Dementia Friendly Keighley The Singing Teapot!": {
          "count": 8,
          "attendances": 49,
          "instances": 69,
          "category": "In-person"
        },
        "Our Patch - Denholme Mural Project": {
          "count": 68,
          "attendances": 95,
          "instances": 167,
          "category": "In-person"
        },
        "Our Patch - Denholme Youth Group": {
          "count": 1,
          "attendances": 10,
          "instances": 18,
          "category": "In-person"
        },
        "Our Patch - Dhol Drumming": {
          "count": 1,
          "attendances": 47,
          "instances": 47,
          "category": "In-person"
        },
        "Our Patch - Doorstep Davincis": {
          "count": 64,
          "attendances": 70,
          "instances": 116,
          "category": "In-person"
        },
        "Our Patch - Get2Gether Group": {
          "count": 17,
          "attendances": 67,
          "instances": 67,
          "category": "In-person"
        },
        "Our Patch - Green Futures: The New Keith Thompson Centre": {
          "count": 233,
          "attendances": 430,
          "instances": 1035,
          "category": "In-person"
        },
        "Our Patch - Hainworth Wood Older People\u2019s Lunch": {
          "count": 21,
          "attendances": 67,
          "instances": 67,
          "category": "In-person"
        },
        "Our Patch - Hainworth Wood: East meets West Cooking": {
          "count": 18,
          "attendances": 18,
          "instances": 18,
          "category": "In-person"
        },
        "Our Patch - Highfield Centre Chit and Chatter Wellbeing Group": {
          "count": 5,
          "attendances": 23,
          "instances": 23,
          "category": "In-person"
        },
        "Our Patch - Holme in the Wood coffee shop and Bierley Church - BD4 Artistes": {
          "count": 20,
          "attendances": 62,
          "instances": 62,
          "category": "In-person"
        },
        "Our Patch - Holmewood Film Project": {
          "count": 13,
          "attendances": 13,
          "instances": 13,
          "category": "In-person"
        },
        "Our Patch - In Other Words": {
          "count": 5,
          "attendances": 11,
          "instances": 11,
          "category": "In-person"
        },
        "Our Patch - K Town Sound Machine": {
          "count": 120,
          "attendances": 165,
          "instances": 825,
          "category": "In-person"
        },
        "Our Patch - KAWACC": {
          "count": 29,
          "attendances": 55,
          "instances": 67,
          "category": "In-person"
        },
        "Our Patch - Lower Grange Choir Grief Support": {
          "count": 47,
          "attendances": 292,
          "instances": 519,
          "category": "In-person"
        },
        "Our Patch - Lower Grange Culture Cafe": {
          "count": 34,
          "attendances": 140,
          "instances": 140,
          "category": "In-person"
        },
        "Our Patch - MAPA Girls Group": {
          "count": 166,
          "attendances": 504,
          "instances": 1054,
          "category": "In-person"
        },
        "Our Patch - MAPA Youth Group": {
          "count": 6,
          "attendances": 17,
          "instances": 17,
          "category": "In-person"
        },
        "Our Patch - Marie Curie Residents Project": {
          "count": 18,
          "attendances": 50,
          "instances": 50,
          "category": "In-person"
        },
        "Our Patch - Masjid Ayesha": {
          "count": 43,
          "attendances": 72,
          "instances": 72,
          "category": "In-person"
        },
        "Our Patch - Motiv8 - What you sayin": {
          "count": 5,
          "attendances": 43,
          "instances": 43,
          "category": "In-person"
        },
        "Our Patch - Musical Stories": {
          "count": 411,
          "attendances": 472,
          "instances": 722,
          "category": "In-person"
        },
        "Our Patch - Northcliffe Environmental Enterprises Team (NEET)": {
          "count": 13,
          "attendances": 68,
          "instances": 232,
          "category": "In-person"
        },
        "Our Patch - One-off community events: East": {
          "count": 845,
          "attendances": 905,
          "instances": 1810,
          "category": "In-person"
        },
        "Our Patch - One-off community events: Keighley & Ilkley": {
          "count": 640,
          "attendances": 701,
          "instances": 2145,
          "category": "In-person"
        },
        "Our Patch - One-off community events: Shipley": {
          "count": 1692,
          "attendances": 1725,
          "instances": 3806,
          "category": "In-person"
        },
        "Our Patch - One-off community events: South": {
          "count": 1233,
          "attendances": 1237,
          "instances": 2400,
          "category": "In-person"
        },
        "Our Patch - One-off community events: West": {
          "count": 136,
          "attendances": 137,
          "instances": 274,
          "category": "In-person"
        },
        "Our Patch - Our Holmewood Mural": {
          "count": 77,
          "attendances": 87,
          "instances": 90,
          "category": "In-person"
        },
        "Our Patch - Parkside Tapestry Project": {
          "count": 27,
          "attendances": 89,
          "instances": 89,
          "category": "In-person"
        },
        "Our Patch - People's Care Movement": {
          "count": 28,
          "attendances": 40,
          "instances": 80,
          "category": "In-person"
        },
        "Our Patch - Ravenscliffe Drumming Workshops": {
          "count": 25,
          "attendances": 87,
          "instances": 87,
          "category": "In-person"
        },
        "Our Patch - Reevy Hill Mural": {
          "count": 45,
          "attendances": 71,
          "instances": 122,
          "category": "In-person"
        },
        "Our Patch - Rhythms on The Road East": {
          "count": 7,
          "attendances": 32,
          "instances": 32,
          "category": "In-person"
        },
        "Our Patch - Roots & Fruits": {
          "count": 67,
          "attendances": 283,
          "instances": 334,
          "category": "In-person"
        },
        "Our Patch - Roshni Ghar Wellbeing Group": {
          "count": 26,
          "attendances": 39,
          "instances": 39,
          "category": "In-person"
        },
        "Our Patch - Sangat Centre - Keighley Central - Mens Over 50s": {
          "count": 3,
          "attendances": 45,
          "instances": 50,
          "category": "In-person"
        },
        "Our Patch - Scouts and Cubs at St James Church Hall": {
          "count": 113,
          "attendances": 227,
          "instances": 454,
          "category": "In-person"
        },
        "Our Patch - Singing for Wellbeing at The Good Shepherd Centre": {
          "count": 16,
          "attendances": 75,
          "instances": 75,
          "category": "In-person"
        },
        "Our Patch - St Wilfrid's Community Cafe - Storytelling project": {
          "count": 28,
          "attendances": 79,
          "instances": 79,
          "category": "In-person"
        },
        "Our Patch - St Wilfrids Church - Church Star Project": {
          "count": 29,
          "attendances": 29,
          "instances": 48,
          "category": "In-person"
        },
        "Our Patch - Street Dance (Bolton Woods Centre/Black History Month)": {
          "count": 16,
          "attendances": 33,
          "instances": 33,
          "category": "In-person"
        },
        "Our Patch - Summer Reading Challenge (All Areas)": {
          "count": 487,
          "attendances": 487,
          "instances": 1007,
          "category": "In-person"
        },
        "Our Patch - The Blank Page Club": {
          "count": 19,
          "attendances": 39,
          "instances": 39,
          "category": "In-person"
        },
        "Our Patch - The Bridge - Cultural Care Package": {
          "count": 16,
          "attendances": 25,
          "instances": 50,
          "category": "In-person"
        },
        "Our Patch - The Gateway Centre Weaving Project": {
          "count": 11,
          "attendances": 47,
          "instances": 47,
          "category": "In-person"
        },
        "Our Patch - The Keighley Chorus": {
          "count": 22,
          "attendances": 60,
          "instances": 60,
          "category": "In-person"
        },
        "Our Patch - The Pebble Project": {
          "count": 238,
          "attendances": 239,
          "instances": 239,
          "category": "In-person"
        },
        "Our Patch - The Travelling Spoon": {
          "count": 5,
          "attendances": 24,
          "instances": 118,
          "category": "In-person"
        },
        "Our Patch - The Wellbeing Walkers": {
          "count": 2,
          "attendances": 12,
          "instances": 12,
          "category": "In-person"
        },
        "Our Patch - Tong Village - The Village Van Goghs": {
          "count": 40,
          "attendances": 60,
          "instances": 60,
          "category": "In-person"
        },
        "Our Patch - Tu i Tam Community Visits": {
          "count": 119,
          "attendances": 119,
          "instances": 156,
          "category": "In-person"
        },
        "Our Patch - Urdu Shurdu": {
          "count": 17,
          "attendances": 17,
          "instances": 17,
          "category": "In-person"
        },
        "Our Patch - Us Girls": {
          "count": 6,
          "attendances": 6,
          "instances": 6,
          "category": "In-person"
        },
        "Our Patch - Vibe Check": {
          "count": 10,
          "attendances": 20,
          "instances": 40,
          "category": "In-person"
        },
        "Our Patch - Wibsey Community Garden - BD6 Artistes": {
          "count": 3,
          "attendances": 7,
          "instances": 7,
          "category": "In-person"
        },
        "Our Patch - Wild + Kind": {
          "count": 206,
          "attendances": 209,
          "instances": 230,
          "category": "In-person"
        },
        "Our Patch - Windhill Seniors Group": {
          "count": 6,
          "attendances": 40,
          "instances": 74,
          "category": "In-person"
        },
        "Our Patch - Woodroyd Tapestry Project": {
          "count": 19,
          "attendances": 43,
          "instances": 43,
          "category": "In-person"
        },
        "Our Patch - Youth Zen Den": {
          "count": 4,
          "attendances": 47,
          "instances": 47,
          "category": "In-person"
        },
        "PLAY Facilitators @ Beacon (all)": {
          "count": 1352,
          "attendances": 1352,
          "instances": 1352,
          "category": "In-person"
        },
        "PLAY: Alive & Kicking Drama Adventures": {
          "count": 480,
          "attendances": 0,
          "instances": 840,
          "category": "In-person"
        },
        "PLAY: Intergenerational Play": {
          "count": 97,
          "attendances": 106,
          "instances": 261,
          "category": "In-person"
        },
        "PLAY: REPLAY": {
          "count": 23,
          "attendances": 23,
          "instances": 23,
          "category": "In-person"
        },
        "PLAY: Science Explorers Play Lab": {
          "count": 115,
          "attendances": 0,
          "instances": 115,
          "category": "In-person"
        },
        "PLAY: The Great Adventure Build with Woodland Tribe": {
          "count": 931,
          "attendances": 931,
          "instances": 931,
          "category": "In-person"
        },
        "Peace Picnics (all parks)": {
          "count": 65,
          "attendances": 65,
          "instances": 65,
          "category": "In-person"
        },
        "Poetry Takeaway": {
          "count": 262,
          "attendances": 212,
          "instances": 262,
          "category": "In-person"
        },
        "Qigong and Tai Chi Mid Autumn Moon Festival": {
          "count": 123,
          "attendances": 123,
          "instances": 123,
          "category": "In-person"
        },
        "Re:Born": {
          "count": 9,
          "attendances": 9,
          "instances": 9,
          "category": "Exhibition"
        },
        "STRIKE": {
          "count": 152,
          "attendances": 215,
          "instances": 741,
          "category": "In-person"
        },
        "Say It As It Is (Cliffe Castle)": {
          "count": 10,
          "attendances": 10,
          "instances": 10,
          "category": "In-person"
        },
        "Share Your Story at Beacon (National Literacy Trust)": {
          "count": 932,
          "attendances": 425,
          "instances": 932,
          "category": "In-person"
        },
        "Share and Care (Bradford New Church, Frizinghall)": {
          "count": 95,
          "attendances": 0,
          "instances": 95,
          "category": "In-person"
        },
        "Sip and Paint with Creative Flare": {
          "count": 44,
          "attendances": 44,
          "instances": 44,
          "category": "In-person"
        },
        "Spin Arts: RIDE": {
          "count": 366,
          "attendances": 366,
          "instances": 366,
          "category": "In-person"
        },
        "The Invite by Mind the Gap": {
          "count": 15,
          "attendances": 15,
          "instances": 15,
          "category": "In-person"
        },
        "The Portrait of Mai: Youth Engagement Programme": {
          "count": 66,
          "attendances": 0,
          "instances": 132,
          "category": "Exhibition"
        },
        "The Railway Children": {
          "count": 4436,
          "attendances": 5046,
          "instances": 5636,
          "category": "In-person"
        },
        "Tu i Tam / Tyt i Tam: Tim Smith & Lodz Fotofestival": {
          "count": 76,
          "attendances": 68,
          "instances": 76,
          "category": "Exhibition"
        },
        "Turner Prize": {
          "count": 347,
          "attendances": 85,
          "instances": 475,
          "category": "Exhibition"
        },
        "We Will Sing by Ann Hamilton at Salt's Mill": {
          "count": 48,
          "attendances": 28,
          "instances": 160,
          "category": "Exhibition"
        },
        "Wild Uplands": {
          "count": 867,
          "attendances": 663,
          "instances": 1091,
          "category": "Exhibition"
        },
        "Wonky Olympics": {
          "count": 44,
          "attendances": 44,
          "instances": 44,
          "category": "In-person"
        },
        "Your Best Guess": {
          "count": 28,
          "attendances": 28,
          "instances": 28,
          "category": "In-person"
        },
        "Zee and the City": {
          "count": 728,
          "attendances": 760,
          "instances": 760,
          "category": "In-person"
        }
      }
    },
    "training_and_skills_development_participants": {
      "count": 2048,
      "by_project": {
        "Bradford Producing Hub": {
          "count": 138,
          "category": null
        },
        "Creative Health": {
          "count": 278,
          "category": null
        },
        "Digital Creatives scheme": {
          "count": 1632,
          "category": null
        }
      }
    },
    "cultural_learning_participants": {
      "count": 2324,
      "by_project": {
        "Bradford Made MASTER": {
          "count": 60,
          "category": null
        },
        "Bradford on Foot": {
          "count": 55,
          "category": null
        },
        "Compagnie Off: Giraffes": {
          "count": 10,
          "category": null
        },
        "Ice Age Art Now": {
          "count": 204,
          "category": null
        },
        "Our Patch - Baildon Carnival - Banner Making": {
          "count": 25,
          "category": null
        },
        "PLAY: Alive & Kicking Drama Adventures": {
          "count": 480,
          "category": null
        },
        "PLAY: Intergenerational Play": {
          "count": 71,
          "category": null
        },
        "PLAY: Science Explorers Play Lab": {
          "count": 115,
          "category": null
        },
        "Poetry Takeaway": {
          "count": 50,
          "category": null
        },
        "STRIKE": {
          "count": 72,
          "category": null
        },
        "Share Your Story at Beacon (National Literacy Trust)": {
          "count": 507,
          "category": null
        },
        "Share and Care (Bradford New Church, Frizinghall)": {
          "count": 95,
          "category": null
        },
        "The Portrait of Mai: Youth Engagement Programme": {
          "count": 66,
          "category": null
        },
        "The Railway Children": {
          "count": 20,
          "category": null
        },
        "Tu i Tam / Tyt i Tam: Tim Smith & Lodz Fotofestival": {
          "count": 8,
          "category": null
        },
        "Turner Prize": {
          "count": 262,
          "category": null
        },
        "We Will Sing by Ann Hamilton at Salt's Mill": {
          "count": 20,
          "category": null
        },
        "Wild Uplands": {
          "count": 204,
          "category": null
        }
      }
    }
  },
  "cultural_learning": {
    "participants": 2324,
    "participant_attenances": 2803,
    "schools_engaged": 54
  },
  "volunteers": {
    "total": 2353,
    "people": {
      "checkpoints": {
        "1. Monitoring & Evaluation": 553,
        "2. Sign Up to Induction": 719,
        "3. Fully Inducted Volunteers": 1081,
        "Bradford2025 Turner Prize": 10,
        "Deactivated": 50,
        "Dummy Account for Admin Sign-ins": 13,
        "MISSING": 20,
        "Rosterfy Prison": 1
      }
    }
  }
}