[
  {
    "Date": "2025-01",
    "value": 2885
  },
  {
    "Date": "2025-02",
    "value": 2295
  },
  {
    "Date": "2025-03",
    "value": 5249
  },
  {
    "Date": "2025-04",
    "value": 13308
  },
  {
    "Date": "2025-05",
    "value": 14385
  },
  {
    "Date": "2025-06",
    "value": 6339
  },
  {
    "Date": "2025-07",
    "value": 11263
  },
  {
    "Date": "2025-08",
    "value": 6952
  },
  {
    "Date": "2025-09",
    "value": 7481
  },
  {
    "Date": "2025-10",
    "value": 225
  }
]