{
  "total": 500588,
  "by_category": {
    "Exhibition": 161742,
    "Film": 7927,
    "In-person": 330919
  },
  "by_project": {
    "BBC Introducing at The Underground": {
      "category": "In-person",
      "count": 98
    },
    "BBC: Not Even Water Live (Podcast Recording)": {
      "category": "In-person",
      "count": 40
    },
    "Bradford A City of Film: The Bigger Picture @ Pictureville Seasons - Northern Soul": {
      "category": "Film",
      "count": 750
    },
    "DRAW! (How to Films & non-Our Patch Events)": {
      "category": "In-person",
      "count": 22100
    },
    "Dragons - Eun-Me Ahn Company": {
      "category": "In-person",
      "count": 1274
    },
    "Elevate - Heritage Skills Project": {
      "category": "In-person",
      "count": 10
    },
    "Fighting To Be Heard": {
      "category": "Exhibition",
      "count": 15904
    },
    "I AM ME": {
      "category": "In-person",
      "count": 23224
    },
    "Jungle Book ReImagined - Akram Khan Company": {
      "category": "In-person",
      "count": 1794
    },
    "Loading Bay Programme": {
      "category": "Exhibition, In-person",
      "count": 11230
    },
    "Music Series": {
      "category": "Film",
      "count": 1144
    },
    "Nationhood: Memory and Hope": {
      "category": "Exhibition",
      "count": 12105
    },
    "Northern Soul (Clio Barnard)": {
      "category": "Film",
      "count": 869
    },
    "Our Patch": {
      "category": "In-person",
      "count": 2199
    },
    "PLAY Programme": {
      "category": "In-person",
      "count": 2183
    },
    "Pictureville Screenings": {
      "category": "Film",
      "count": 5164
    },
    "Ramadan Pavillion": {
      "category": "In-person",
      "count": 250794
    },
    "Rise": {
      "category": "In-person",
      "count": 24635
    },
    "Sponsorship - Business Breakfast": {
      "category": "In-person",
      "count": 35
    },
    "Sponsorship - Loading Bay Funder": {
      "category": "In-person",
      "count": 27
    },
    "Sponsorship - Northern Trains": {
      "category": "In-person",
      "count": 40
    },
    "Sponsorship - Yorkshire Water": {
      "category": "In-person",
      "count": 35
    },
    "The Dreams I Had: Andrea Dunbar": {
      "category": "In-person",
      "count": 979
    },
    "Where It Began \u2013 Osman Yousefzada": {
      "category": "Exhibition",
      "count": 108955
    },
    "Wild Uplands": {
      "category": "Exhibition",
      "count": 15000
    }
  },
  "ticketed": {
    "sold": {
      "total": 29493,
      "bradford": 15592
    }
  }
}