{
  "total": 134987,
  "by_category": {
    "": 0,
    "Exhibition": 62279,
    "Festival": 3886,
    "Film": 4384,
    "In-person": 44438,
    "Outdoor arts": 20000
  },
  "by_project": {
    "A Screen Near You - Cinema for All (grassroots development and screening)": 0,
    "A Screen Near You - The Incredible Moving Cinema": 833,
    "ARCHIVE: How Soon Is Now (grant dependent)": 0,
    "Akram Khan and Dance United - Memories of the Future": 0,
    "An Evening with Resi/Dance @ The Beacon (Dance United)": 86,
    "An Evening with: Jacqui Dankworth": 155,
    "Aswad Arts Presents StreetSounds \"LIVE\" Bhangra Niche Set \"LIVE\"": 86,
    "At The 1 in 12": 159,
    "BBC Extraordinary Portraits": 3163,
    "BBC Introducing @ The Beacon": 126,
    "BBC Introducing at The Underground": 0,
    "BD: Walls": 0,
    "Back In The Pink - Castles In The Sky": 0,
    "Basel Zaraa - Moomins": 486,
    "Bassline Symphony": 60,
    "Beacon": 0,
    "Beacon Church Community Cuppa": 0,
    "Big Brass Blowout": 1260,
    "Big Quiffy Bingo": 124,
    "Big Screen - Cannon Mills": 382,
    "Bloom Vicky Amudeme": 0,
    "Bradford Belles": 146,
    "Bradford Literature Festival - New Commissions": 0,
    "Bradford Literature Festival @ Loading Bay": 0,
    "Bradford Made MASTER": 0,
    "Bradford Poetry Slam 2025": 158,
    "Bradford Producing Hub": 0,
    "Bradford Sanctuary Seekers Education Awards 2025": 0,
    "Bradford Selection": 0,
    "Bradford South Young Peoples Celebration (Youth Service)": 70,
    "Bradford on Foot": 0,
    "Bradford's Bigger Picture - Pictureville Year Round Programme": 0,
    "Bradford: A City of Film": 0,
    "CBeebies Bedtime Story Day": 500,
    "Channels (Bodies of Water) - Turbynes": 0,
    "Claytime": 227,
    "Club Ekta Events": 46,
    "Comma Press 'Book of the City'": 0,
    "Common/Wealth: Public Interest": 1126,
    "Connecting Communities": 0,
    "Creative Health": 0,
    "Cricket Tournament Awards Ceremony": 0,
    "Cultural Learning Steering Group": 0,
    "Curious Investigators": 245,
    "DRAW & Messy Play": 0,
    "DRAW!": 0,
    "Dancing with Colours": 47,
    "David Hockney: Pieced Together": 6624,
    "Daytimers (Heritage Bradford stories)": 0,
    "Digital Creatives": 0,
    "Digital Map": 0,
    "Earth & Sky (part of Wild Uplands)": 0,
    "Easter Fun and Celebration": 421,
    "Eggs Collective Dark Nights": 0,
    "Elevate - Heritage Skills Project": 0,
    "Eliza Carthy": 175,
    "FRESH Workshops": 0,
    "Fighting To Be Heard": 5249,
    "Forge - Practical Anarchy": 0,
    "Forge - Scraps": 0,
    "Frontline 1984-1985 by Victor Wedderburn": 2134,
    "Greed - Tavaziva Dance": 29,
    "Happy Hype": 39,
    "I Am Me": 8001,
    "Ice Age Art Now": 0,
    "Immersive Arts UK Conference": 0,
    "International Roma Day Celebration": 67,
    "Intro to Comedy Workshop Series with Alex Dunlop": 0,
    "It's Your Round": 89,
    "Language: No Broblem - Shubbak Festival": 0,
    "Launchpad Music Industry Careers Day": 0,
    "Lay Down Your Burdens": 123,
    "Les Enfants Terribles - A Gameshow for Awful Children": 150,
    "Let's Make": 0,
    "Little Wimmin": 129,
    "Loaded Laughs (#2)": 120,
    "Loud and Proud Dohl Drumming": 0,
    "Meet Our Mothers": 0,
    "Multicultural Pentecost Party": 1473,
    "Museums for Play and Growth": 0,
    "Nadine Shah @ St. Georges Hall": 650,
    "Nationhood: Memory and Hope": 3679,
    "New Focus: Bradford Young Curators": 0,
    "New Music Biennial": 2626,
    "Osman Scuplture": 20000,
    "Our Patch": 3123,
    "PLAY Facilitators @ Beacon (all)": 2,
    "PLAY: Intergenerational Play": 0,
    "PLAY: Red Ball Project (WOW)": 28623,
    "PLAY: The Great Adventure Build with Woodland Tribe": 100,
    "Palettes (International)": 896,
    "Peace Picnics": 81,
    "Penguin": 0,
    "Pictureville - Pauline Black: A 2-Tone Story [+ Q&A]": 0,
    "Pictureville Screenings": 4384,
    "Pictureville Screenings - 'Brought to Life' Season": 0,
    "Pictureville Screenings - Cine Spotlights": 0,
    "Pictureville Screenings - Film4 Curated Season": 0,
    "Pictureville Screenings - Northern Youth Film Season": 0,
    "Pictureville Screenings - Time and Place (Invisible Women)": 0,
    "Pop": 204,
    "Pop Up Family Pride": 200,
    "Punjabi Heritage and Culture by Saath": 95,
    "Qawalli Night at The Beacon": 163,
    "Ramadan Pavillion": 0,
    "Robyn Hood - Fidget Theatre": 164,
    "Roshni": 104,
    "Royal Visit": 0,
    "Sarab": 0,
    "Say It As It Is - Bowling": 0,
    "Say It As It Is - Wibsey": 119,
    "Share Your Story at Beacon (National Literacy Trust)": 282,
    "Sing, Dance, Leap": 0,
    "Sisters 360": 146,
    "So Far, So Good - Yorkshire Dance - as part of BD FEST": 0,
    "Spin Arts: RIDE": 0,
    "Sustenance the Power of Food": 24,
    "Tape Letters": 709,
    "Tech Styles @ The Beacon": 159,
    "Teen Scene Party": 0,
    "Testo": 209,
    "The 56": 164,
    "The Belgrave House Band - Back to Black": 0,
    "The Big Thing - Immersive Arts": 0,
    "The Bradford Progress": 0,
    "The Portrait of Mai: Youth Engagement Programme": 0,
    "The Railway Children": 0,
    "The Sticky Dance": 50,
    "The Tiger Lillies": 149,
    "Tour the Writer": 0,
    "Tower of Now Engagement Strand": 0,
    "Tower of Now: Saad Qureshi (programme strand)": 0,
    "Toxic - Dibby Theatre": 165,
    "Tu i Tam / Tyt i Tam: Tim Smith & Lodz Fotofestival": 0,
    "WOW Community Partnership": 159,
    "Wandering Imaginations: Emerging Fantasy Writer Exchange": 0,
    "We Will Sing by Ann Hamilton at Salt's Mill": 19708,
    "West Yorkshire Young Poet Laureate": 109,
    "Whine List": 124,
    "Wild Uplands": 0,
    "Wonky Olympics": 44,
    "YOU:MATTER": 13012,
    "Youth Club in Bowling Park (closed event)": 0,
    "Youthology": 171,
    "asses.masses": 82,
    "zz - Beacon - Non-project related venue activity": 0,
    "zz - Loading Bay Venue Activity (non-project related)": 0
  },
  "ticketed": {
    "sold": {
      "total": 25888,
      "bradford": 11560,
      "by_project": {
        "An Evening with Jacqui Dankworth": 180,
        "BBC Introducing @ The Beacon": 174,
        "BBC Introducing at The Underground": 41,
        "Back to Black": 122,
        "Bantam's Drift": 142,
        "Bassline Symphony": 1553,
        "Big Quiffy Bingo": 93,
        "Bradford on Foot: Goit Stock with Shanaz Gulzar": 1,
        "Bradford on Foot: Undercliffe Cemetery": 26,
        "Brass on a Sunday Afternoon ": 257,
        "CBeebies Bedtime Stories Day": 1502,
        "Chasing Sunlight": 282,
        "Claytime": 248,
        "Curious Investigators": 313,
        "DANCE SUITE": 267,
        "DJ Marco - Balkan Beats & Brass": 201,
        "Dancing with Colours": 55,
        "Dhamaal \u2013 Core": 267,
        "EGGS COLLECTIVE'S DARK NIGHTS": 70,
        "Earth & Sky": 28,
        "Echoes of the North": 282,
        "Eliza Carthy": 209,
        "Everything for Everyone": 199,
        "Film: Amar Akbar Anthony": 65,
        "Film: Bajrangi Bhaijaan": 27,
        "Film: Barbie": 123,
        "Film: Big Hero 6": 142,
        "Film: Bride and Prejudice": 48,
        "Film: Conclave": 221,
        "Film: Dil Dhadakne Do": 19,
        "Film: Everything Everywhere All at Once": 135,
        "Film: Fantastic Mr. Fox": 128,
        "Film: Flow": 272,
        "Film: Jab We Met": 128,
        "Film: Pulp Fiction": 55,
        "Film: Raiders of the Lost Ark": 9,
        "Film: Speed": 96,
        "Film: The Apartment": 9,
        "Film: The Apartment ": 29,
        "Film: The Greatest Showman": 258,
        "Film: The Lorax": 220,
        "Film: The Matrix": 128,
        "Film: The Penguin Lessons": 111,
        "Film: The Salt Path (Silver Screen)": 14,
        "Film: The Terminator": 44,
        "Film: The Wild Robot": 76,
        "Film: Zindagi Na Milegi Dobara": 43,
        "GLOW": 282,
        "Greed": 63,
        "Hall Royd Brass Band": 227,
        "Happy Hype": 52,
        "Holocene": 366,
        "Into the Night": 655,
        "Intro to Comedy Workshops": 7,
        "It's Your Round": 117,
        "KOKOROKO": 1223,
        "Language: no broblem": 123,
        "Lanre Bakare - 'We Were There' Book Launch": 204,
        "Lay Down Your Burdens": 195,
        "Lay Down Your Burdens: Workshop": 14,
        "Les Enfants Terribles": 222,
        "Little Wimmin - Figs in Wigs": 337,
        "Loaded Laughs": 160,
        "Love's Letter": 17,
        "MARCH": 241,
        "Marcel Lucont\u2019s Whine List": 162,
        "Mercury Songs": 302,
        "Moth x Human": 249,
        "Museums for Play and Growth": 75,
        "Nadine Shah": 675,
        "Nocturnal Sun": 190,
        "North Street Band": 82,
        "N\u2019dehou": 241,
        "Oranje Brass \u2013 Amazing Music From The Netherlands": 200,
        "PLAY: The Great Adventure Build - Home Education": 54,
        "PLAY: The Great Adventure Build - Schools": 128,
        "PLAY: The Great Adventure Build with Woodland Tribe": 1024,
        "Palettes": 410,
        "Peace": 224,
        "Penguin": 96,
        "Penumbra": 191,
        "Public Interest": 1254,
        "Public Interest Club Night": 55,
        "Public Interest: Access Opening Event": 4,
        "Qawwali Night at The Beacon": 201,
        "Reggae & Brass": 230,
        "Requiem": 202,
        "Richard Hawley / Black Dyke Band": 1510,
        "Rizwan-Muazzam Qawwali Group": 437,
        "Robyn Hood": 185,
        "Roshni": 140,
        "Sarab": 3,
        "Say It As It Is": 187,
        "Sisters 360": 184,
        "Summer Solstice Solace": 30,
        "TESTO": 270,
        "Thar Farraige (Over Sea)": 222,
        "The 56": 202,
        "The Pahari-Pothwari Literature Project Showcase": 197,
        "The Path": 683,
        "The Sticky Dance": 57,
        "The Sticky Dance for autistic & neurodivergent children": 18,
        "The Tiger Lillies": 197,
        "Threads of Sound: A Woollen Heritage": 270,
        "Toxic": 207,
        "Voice Notes": 190,
        "Wallace & Gromit: The Wrong Trousers - Live": 616,
        "Yearn - Sipho": 293,
        "asses.masses": 120,
        "asses.masses: Game Making Workshop": 4
      },
      "by_geo": {
        "E06000001": 5,
        "E06000003": 6,
        "E06000004": 2,
        "E06000005": 4,
        "E06000007": 8,
        "E06000008": 15,
        "E06000009": 2,
        "E06000010": 209,
        "E06000011": 70,
        "E06000012": 5,
        "E06000013": 10,
        "E06000014": 107,
        "E06000015": 17,
        "E06000016": 2,
        "E06000017": 2,
        "E06000018": 17,
        "E06000019": 4,
        "E06000021": 4,
        "E06000022": 2,
        "E06000023": 18,
        "E06000025": 14,
        "E06000032": 3,
        "E06000033": 10,
        "E06000037": 3,
        "E06000039": 1,
        "E06000040": 2,
        "E06000041": 4,
        "E06000043": 12,
        "E06000046": 2,
        "E06000047": 4,
        "E06000049": 10,
        "E06000050": 15,
        "E06000051": 11,
        "E06000054": 5,
        "E06000055": 1,
        "E06000056": 2,
        "E06000057": 11,
        "E06000058": 2,
        "E06000060": 9,
        "E06000061": 2,
        "E06000062": 6,
        "E06000063": 18,
        "E06000064": 22,
        "E06000065": 477,
        "E06000066": 8,
        "E07000008": 11,
        "E07000011": 10,
        "E07000012": 1,
        "E07000032": 10,
        "E07000033": 1,
        "E07000034": 2,
        "E07000035": 2,
        "E07000037": 12,
        "E07000038": 4,
        "E07000039": 4,
        "E07000040": 4,
        "E07000044": 1,
        "E07000062": 3,
        "E07000067": 2,
        "E07000071": 2,
        "E07000073": 2,
        "E07000078": 4,
        "E07000079": 2,
        "E07000087": 1,
        "E07000099": 3,
        "E07000103": 3,
        "E07000109": 1,
        "E07000111": 2,
        "E07000113": 2,
        "E07000114": 2,
        "E07000117": 5,
        "E07000118": 4,
        "E07000119": 2,
        "E07000120": 1,
        "E07000121": 3,
        "E07000122": 33,
        "E07000123": 9,
        "E07000124": 10,
        "E07000125": 6,
        "E07000126": 6,
        "E07000127": 2,
        "E07000128": 4,
        "E07000132": 2,
        "E07000134": 2,
        "E07000137": 2,
        "E07000138": 4,
        "E07000139": 4,
        "E07000140": 2,
        "E07000141": 2,
        "E07000142": 6,
        "E07000147": 2,
        "E07000148": 5,
        "E07000170": 2,
        "E07000171": 13,
        "E07000173": 4,
        "E07000176": 4,
        "E07000177": 5,
        "E07000178": 7,
        "E07000179": 6,
        "E07000193": 3,
        "E07000194": 2,
        "E07000198": 7,
        "E07000209": 2,
        "E07000210": 6,
        "E07000213": 2,
        "E07000215": 11,
        "E07000216": 14,
        "E07000218": 2,
        "E07000221": 4,
        "E07000222": 4,
        "E07000229": 2,
        "E07000235": 2,
        "E07000241": 1,
        "E07000244": 9,
        "E08000001": 9,
        "E08000002": 105,
        "E08000003": 138,
        "E08000004": 39,
        "E08000005": 26,
        "E08000006": 11,
        "E08000007": 18,
        "E08000008": 13,
        "E08000009": 36,
        "E08000010": 10,
        "E08000012": 29,
        "E08000013": 2,
        "E08000014": 5,
        "E08000015": 9,
        "E08000016": 32,
        "E08000017": 43,
        "E08000018": 99,
        "E08000019": 218,
        "E08000021": 18,
        "E08000022": 6,
        "E08000023": 2,
        "E08000024": 3,
        "E08000025": 13,
        "E08000026": 3,
        "E08000027": 9,
        "E08000029": 6,
        "E08000031": 3,
        "E08000032": 11560,
        "E08000033": 1018,
        "E08000034": 606,
        "E08000035": 2172,
        "E08000036": 106,
        "E09000003": 7,
        "E09000005": 5,
        "E09000006": 9,
        "E09000007": 3,
        "E09000008": 9,
        "E09000009": 11,
        "E09000011": 7,
        "E09000012": 25,
        "E09000013": 13,
        "E09000014": 12,
        "E09000015": 4,
        "E09000018": 6,
        "E09000019": 9,
        "E09000022": 14,
        "E09000023": 18,
        "E09000025": 2,
        "E09000026": 2,
        "E09000028": 180,
        "E09000030": 10,
        "E09000031": 2,
        "E09000032": 8,
        "E09000033": 3,
        "MISSING": 7391,
        "N09000003": 4,
        "N09000006": 2,
        "S12000005": 2,
        "S12000006": 1,
        "S12000008": 1,
        "S12000010": 4,
        "S12000017": 12,
        "S12000019": 5,
        "S12000026": 6,
        "S12000036": 120,
        "S12000038": 1,
        "S12000042": 2,
        "S12000049": 39,
        "UNMATCHED": 59,
        "W06000002": 6,
        "W06000003": 10,
        "W06000012": 4,
        "W06000015": 5,
        "W06000021": 2,
        "W06000023": 4
      }
    },
    "scanned": {
      "total": {
        "sold": 8547,
        "scanned": 0
      }
    }
  },
  "unticketed": null
}